Workbook

Sheet Readme
A1: Fabric AI Readiness Assessment
A3: Rule pack version | B3: 2026.09.1
A4: Spec version | B4: 1.0.0
A5: Rules | B5: 138
A6: Updated | B6: 2026-09-10
A7: Purpose | B7: Config-driven rule pack measuring enablement, usage, response validity/relevance and performance posture for Power BI Copilot and Microsoft Fabric data agents. Designed so that AI query generation is narrowly scoped and grounded rather than broad-scanning an unconstrained schema.
A9: HOW TO USE
A10: 1 | B10: Work through one area tab at a time. Each row is one rule.
A11: 2 | B11: Set the yellow Result cell on every row: pass, partial, fail, na, or unknown.
A12: 3 | B12: Record where the evidence lives, who owns the fix, and the target date in the other yellow cells.
A13: 4 | B13: The Scoring tab recalculates live. Read the overall score and maturity level there.
A14: 5 | B14: Any blocker rule left at fail or unknown gates the maturity level at 0 regardless of score.
A16: EDIT ONLY THE YELLOW CELLS | B16: Every other cell restates the rule and should not be changed here. To change a rule, edit AssessmentRules.json and regenerate this workbook.
A17: THIS IS A VIEW, NOT THE SOURCE | B17: AssessmentRules.json is the source of truth. Add your own rules to rules/custom/*.json and rebuild.
A19: RESULT STATES
A20: pass | B20: Requirement met and evidenced. (credit 1.0)
A21: partial | B21: Partially met, e.g. applied to some models/agents but not all in scope. (credit 0.5)
A22: fail | B22: Requirement not met. (credit 0.0)
A23: na | B23: Out of scope for this estate; removed from both numerator and denominator. (excluded from scoring)
A24: unknown | B24: Not yet assessed. Scored as fail but reported separately as assessment debt. (credit 0.0)
A26: SEVERITY WEIGHTS
A27: blocker | B27: weight 13 - GATES the maturity level. AI features cannot function or cannot be trusted at all until fixed. A failed blocker caps overall maturity at Not Ready.
A28: critical | B28: weight 8. Materially wrong answers, security exposure, or severe cost/latency. Fix before broad rollout.
A29: high | B29: weight 5. Frequent ambiguity, degraded relevance, or avoidable capacity burn.
A30: medium | B30: weight 3. Noticeable quality or efficiency loss; fix during hardening.
A31: low | B31: weight 1. Polish and consistency; improves long-run maintainability.
A33: BASIS COLUMN
A34: documented | B34: Stated in a cited source. Treat the threshold as authoritative but re-verify against current docs.
A35: inferred | B35: Engineering judgement built on cited platform behaviour. Calibrate to your own risk appetite.
A36: community | B36: Unofficial. Verify before relying on it.

Sheet Scoring
A1: Readiness score
A3: Area | B3: Score % | C3: Weight | D3: Pass | E3: Partial | F3: Fail | G3: N/A | H3: Unknown | I3: Earned | J3: Possible
A4: Tenant & admin enablement | B4: =IFERROR(ROUND(100*I4/J4,1),"n/a") -> 0 | C4: 10 | D4: =COUNTIF('Tenant & admin enablement'!$N$3:$N$11,"pass") -> 0 | E4: =COUNTIF('Tenant & admin enablement'!$N$3:$N$11,"partial") -> 0 | F4: =COUNTIF('Tenant & admin enablement'!$N$3:$N$11,"fail") -> 0 | G4: =COUNTIF('Tenant & admin enablement'!$N$3:$N$11,"na") -> 0 | H4: =COUNTIF('Tenant & admin enablement'!$N$3:$N$11,"unknown") -> 9 | I4: =SUMIF('Tenant & admin enablement'!$N$3:$N$11,"pass",'Tenant & admin enablement'!$T$3:$T$11)+0.5*SUMIF('Tenant & admin enablement'!$N$3:$N$11,"partial",'Tenant & admin enablement'!$T$3:$T$11) -> 0 | J4: =SUM('Tenant & admin enablement'!$T$3:$T$11)-SUMIF('Tenant & admin enablement'!$N$3:$N$11,"na",'Tenant & admin enablement'!$T$3:$T$11) -> 63
A5: Capacity, SKU, region & cost | B5: =IFERROR(ROUND(100*I5/J5,1),"n/a") -> 0 | C5: 10 | D5: =COUNTIF('Capacity, SKU, region & cost'!$N$3:$N$8,"pass") -> 0 | E5: =COUNTIF('Capacity, SKU, region & cost'!$N$3:$N$8,"partial") -> 0 | F5: =COUNTIF('Capacity, SKU, region & cost'!$N$3:$N$8,"fail") -> 0 | G5: =COUNTIF('Capacity, SKU, region & cost'!$N$3:$N$8,"na") -> 0 | H5: =COUNTIF('Capacity, SKU, region & cost'!$N$3:$N$8,"unknown") -> 6 | I5: =SUMIF('Capacity, SKU, region & cost'!$N$3:$N$8,"pass",'Capacity, SKU, region & cost'!$T$3:$T$8)+0.5*SUMIF('Capacity, SKU, region & cost'!$N$3:$N$8,"partial",'Capacity, SKU, region & cost'!$T$3:$T$8) -> 0 | J5: =SUM('Capacity, SKU, region & cost'!$T$3:$T$8)-SUMIF('Capacity, SKU, region & cost'!$N$3:$N$8,"na",'Capacity, SKU, region & cost'!$T$3:$T$8) -> 50
A6: Workspace & item governance | B6: =IFERROR(ROUND(100*I6/J6,1),"n/a") -> 0 | C6: 6 | D6: =COUNTIF('Workspace & item governance'!$N$3:$N$9,"pass") -> 0 | E6: =COUNTIF('Workspace & item governance'!$N$3:$N$9,"partial") -> 0 | F6: =COUNTIF('Workspace & item governance'!$N$3:$N$9,"fail") -> 0 | G6: =COUNTIF('Workspace & item governance'!$N$3:$N$9,"na") -> 0 | H6: =COUNTIF('Workspace & item governance'!$N$3:$N$9,"unknown") -> 7 | I6: =SUMIF('Workspace & item governance'!$N$3:$N$9,"pass",'Workspace & item governance'!$T$3:$T$9)+0.5*SUMIF('Workspace & item governance'!$N$3:$N$9,"partial",'Workspace & item governance'!$T$3:$T$9) -> 0 | J6: =SUM('Workspace & item governance'!$T$3:$T$9)-SUMIF('Workspace & item governance'!$N$3:$N$9,"na",'Workspace & item governance'!$T$3:$T$9) -> 35
A7: AI data schema & scope reduction | B7: =IFERROR(ROUND(100*I7/J7,1),"n/a") -> 0 | C7: 14 | D7: =COUNTIF('AI data schema & scope reductio'!$N$3:$N$23,"pass") -> 0 | E7: =COUNTIF('AI data schema & scope reductio'!$N$3:$N$23,"partial") -> 0 | F7: =COUNTIF('AI data schema & scope reductio'!$N$3:$N$23,"fail") -> 0 | G7: =COUNTIF('AI data schema & scope reductio'!$N$3:$N$23,"na") -> 0 | H7: =COUNTIF('AI data schema & scope reductio'!$N$3:$N$23,"unknown") -> 21 | I7: =SUMIF('AI data schema & scope reductio'!$N$3:$N$23,"pass",'AI data schema & scope reductio'!$T$3:$T$23)+0.5*SUMIF('AI data schema & scope reductio'!$N$3:$N$23,"partial",'AI data schema & scope reductio'!$T$3:$T$23) -> 0 | J7: =SUM('AI data schema & scope reductio'!$T$3:$T$23)-SUMIF('AI data schema & scope reductio'!$N$3:$N$23,"na",'AI data schema & scope reductio'!$T$3:$T$23) -> 127
A8: Semantic model structure | B8: =IFERROR(ROUND(100*I8/J8,1),"n/a") -> 0 | C8: 12 | D8: =COUNTIF('Semantic model structure'!$N$3:$N$12,"pass") -> 0 | E8: =COUNTIF('Semantic model structure'!$N$3:$N$12,"partial") -> 0 | F8: =COUNTIF('Semantic model structure'!$N$3:$N$12,"fail") -> 0 | G8: =COUNTIF('Semantic model structure'!$N$3:$N$12,"na") -> 0 | H8: =COUNTIF('Semantic model structure'!$N$3:$N$12,"unknown") -> 10 | I8: =SUMIF('Semantic model structure'!$N$3:$N$12,"pass",'Semantic model structure'!$T$3:$T$12)+0.5*SUMIF('Semantic model structure'!$N$3:$N$12,"partial",'Semantic model structure'!$T$3:$T$12) -> 0 | J8: =SUM('Semantic model structure'!$T$3:$T$12)-SUMIF('Semantic model structure'!$N$3:$N$12,"na",'Semantic model structure'!$T$3:$T$12) -> 55
A9: Names, descriptions & linguistics | B9: =IFERROR(ROUND(100*I9/J9,1),"n/a") -> 0 | C9: 11 | D9: =COUNTIF('Names, descriptions & linguisti'!$N$3:$N$12,"pass") -> 0 | E9: =COUNTIF('Names, descriptions & linguisti'!$N$3:$N$12,"partial") -> 0 | F9: =COUNTIF('Names, descriptions & linguisti'!$N$3:$N$12,"fail") -> 0 | G9: =COUNTIF('Names, descriptions & linguisti'!$N$3:$N$12,"na") -> 0 | H9: =COUNTIF('Names, descriptions & linguisti'!$N$3:$N$12,"unknown") -> 10 | I9: =SUMIF('Names, descriptions & linguisti'!$N$3:$N$12,"pass",'Names, descriptions & linguisti'!$T$3:$T$12)+0.5*SUMIF('Names, descriptions & linguisti'!$N$3:$N$12,"partial",'Names, descriptions & linguisti'!$T$3:$T$12) -> 0 | J9: =SUM('Names, descriptions & linguisti'!$T$3:$T$12)-SUMIF('Names, descriptions & linguisti'!$N$3:$N$12,"na",'Names, descriptions & linguisti'!$T$3:$T$12) -> 56
A10: Measures & DAX | B10: =IFERROR(ROUND(100*I10/J10,1),"n/a") -> 0 | C10: 9 | D10: =COUNTIF('Measures & DAX'!$N$3:$N$14,"pass") -> 0 | E10: =COUNTIF('Measures & DAX'!$N$3:$N$14,"partial") -> 0 | F10: =COUNTIF('Measures & DAX'!$N$3:$N$14,"fail") -> 0 | G10: =COUNTIF('Measures & DAX'!$N$3:$N$14,"na") -> 0 | H10: =COUNTIF('Measures & DAX'!$N$3:$N$14,"unknown") -> 12 | I10: =SUMIF('Measures & DAX'!$N$3:$N$14,"pass",'Measures & DAX'!$T$3:$T$14)+0.5*SUMIF('Measures & DAX'!$N$3:$N$14,"partial",'Measures & DAX'!$T$3:$T$14) -> 0 | J10: =SUM('Measures & DAX'!$T$3:$T$14)-SUMIF('Measures & DAX'!$N$3:$N$14,"na",'Measures & DAX'!$T$3:$T$14) -> 59
A11: Data types & data quality | B11: =IFERROR(ROUND(100*I11/J11,1),"n/a") -> 0 | C11: 5 | D11: =COUNTIF('Data types & data quality'!$N$3:$N$7,"pass") -> 0 | E11: =COUNTIF('Data types & data quality'!$N$3:$N$7,"partial") -> 0 | F11: =COUNTIF('Data types & data quality'!$N$3:$N$7,"fail") -> 0 | G11: =COUNTIF('Data types & data quality'!$N$3:$N$7,"na") -> 0 | H11: =COUNTIF('Data types & data quality'!$N$3:$N$7,"unknown") -> 5 | I11: =SUMIF('Data types & data quality'!$N$3:$N$7,"pass",'Data types & data quality'!$T$3:$T$7)+0.5*SUMIF('Data types & data quality'!$N$3:$N$7,"partial",'Data types & data quality'!$T$3:$T$7) -> 0 | J11: =SUM('Data types & data quality'!$T$3:$T$7)-SUMIF('Data types & data quality'!$N$3:$N$7,"na",'Data types & data quality'!$T$3:$T$7) -> 22
A12: Security, RLS & compliance | B12: =IFERROR(ROUND(100*I12/J12,1),"n/a") -> 0 | C12: 8 | D12: =COUNTIF('Security, RLS & compliance'!$N$3:$N$10,"pass") -> 0 | E12: =COUNTIF('Security, RLS & compliance'!$N$3:$N$10,"partial") -> 0 | F12: =COUNTIF('Security, RLS & compliance'!$N$3:$N$10,"fail") -> 0 | G12: =COUNTIF('Security, RLS & compliance'!$N$3:$N$10,"na") -> 0 | H12: =COUNTIF('Security, RLS & compliance'!$N$3:$N$10,"unknown") -> 8 | I12: =SUMIF('Security, RLS & compliance'!$N$3:$N$10,"pass",'Security, RLS & compliance'!$T$3:$T$10)+0.5*SUMIF('Security, RLS & compliance'!$N$3:$N$10,"partial",'Security, RLS & compliance'!$T$3:$T$10) -> 0 | J12: =SUM('Security, RLS & compliance'!$T$3:$T$10)-SUMIF('Security, RLS & compliance'!$N$3:$N$10,"na",'Security, RLS & compliance'!$T$3:$T$10) -> 51
A13: Verified answers | B13: =IFERROR(ROUND(100*I13/J13,1),"n/a") -> 0 | C13: 6 | D13: =COUNTIF('Verified answers'!$N$3:$N$9,"pass") -> 0 | E13: =COUNTIF('Verified answers'!$N$3:$N$9,"partial") -> 0 | F13: =COUNTIF('Verified answers'!$N$3:$N$9,"fail") -> 0 | G13: =COUNTIF('Verified answers'!$N$3:$N$9,"na") -> 0 | H13: =COUNTIF('Verified answers'!$N$3:$N$9,"unknown") -> 7 | I13: =SUMIF('Verified answers'!$N$3:$N$9,"pass",'Verified answers'!$T$3:$T$9)+0.5*SUMIF('Verified answers'!$N$3:$N$9,"partial",'Verified answers'!$T$3:$T$9) -> 0 | J13: =SUM('Verified answers'!$T$3:$T$9)-SUMIF('Verified answers'!$N$3:$N$9,"na",'Verified answers'!$T$3:$T$9) -> 37
A14: AI instructions | B14: =IFERROR(ROUND(100*I14/J14,1),"n/a") -> 0 | C14: 6 | D14: =COUNTIF('AI instructions'!$N$3:$N$7,"pass") -> 0 | E14: =COUNTIF('AI instructions'!$N$3:$N$7,"partial") -> 0 | F14: =COUNTIF('AI instructions'!$N$3:$N$7,"fail") -> 0 | G14: =COUNTIF('AI instructions'!$N$3:$N$7,"na") -> 0 | H14: =COUNTIF('AI instructions'!$N$3:$N$7,"unknown") -> 5 | I14: =SUMIF('AI instructions'!$N$3:$N$7,"pass",'AI instructions'!$T$3:$T$7)+0.5*SUMIF('AI instructions'!$N$3:$N$7,"partial",'AI instructions'!$T$3:$T$7) -> 0 | J14: =SUM('AI instructions'!$T$3:$T$7)-SUMIF('AI instructions'!$N$3:$N$7,"na",'AI instructions'!$T$3:$T$7) -> 29
A15: Fabric data agent configuration | B15: =IFERROR(ROUND(100*I15/J15,1),"n/a") -> 0 | C15: 10 | D15: =COUNTIF('Fabric data agent configuration'!$N$3:$N$12,"pass") -> 0 | E15: =COUNTIF('Fabric data agent configuration'!$N$3:$N$12,"partial") -> 0 | F15: =COUNTIF('Fabric data agent configuration'!$N$3:$N$12,"fail") -> 0 | G15: =COUNTIF('Fabric data agent configuration'!$N$3:$N$12,"na") -> 0 | H15: =COUNTIF('Fabric data agent configuration'!$N$3:$N$12,"unknown") -> 10 | I15: =SUMIF('Fabric data agent configuration'!$N$3:$N$12,"pass",'Fabric data agent configuration'!$T$3:$T$12)+0.5*SUMIF('Fabric data agent configuration'!$N$3:$N$12,"partial",'Fabric data agent configuration'!$T$3:$T$12) -> 0 | J15: =SUM('Fabric data agent configuration'!$T$3:$T$12)-SUMIF('Fabric data agent configuration'!$N$3:$N$12,"na",'Fabric data agent configuration'!$T$3:$T$12) -> 43
A16: Performance & query efficiency | B16: =IFERROR(ROUND(100*I16/J16,1),"n/a") -> 0 | C16: 9 | D16: =COUNTIF('Performance & query efficiency'!$N$3:$N$10,"pass") -> 0 | E16: =COUNTIF('Performance & query efficiency'!$N$3:$N$10,"partial") -> 0 | F16: =COUNTIF('Performance & query efficiency'!$N$3:$N$10,"fail") -> 0 | G16: =COUNTIF('Performance & query efficiency'!$N$3:$N$10,"na") -> 0 | H16: =COUNTIF('Performance & query efficiency'!$N$3:$N$10,"unknown") -> 8 | I16: =SUMIF('Performance & query efficiency'!$N$3:$N$10,"pass",'Performance & query efficiency'!$T$3:$T$10)+0.5*SUMIF('Performance & query efficiency'!$N$3:$N$10,"partial",'Performance & query efficiency'!$T$3:$T$10) -> 0 | J16: =SUM('Performance & query efficiency'!$T$3:$T$10)-SUMIF('Performance & query efficiency'!$N$3:$N$10,"na",'Performance & query efficiency'!$T$3:$T$10) -> 55
A17: Response validity & relevance | B17: =IFERROR(ROUND(100*I17/J17,1),"n/a") -> 0 | C17: 10 | D17: =COUNTIF('Response validity & relevance'!$N$3:$N$15,"pass") -> 0 | E17: =COUNTIF('Response validity & relevance'!$N$3:$N$15,"partial") -> 0 | F17: =COUNTIF('Response validity & relevance'!$N$3:$N$15,"fail") -> 0 | G17: =COUNTIF('Response validity & relevance'!$N$3:$N$15,"na") -> 0 | H17: =COUNTIF('Response validity & relevance'!$N$3:$N$15,"unknown") -> 13 | I17: =SUMIF('Response validity & relevance'!$N$3:$N$15,"pass",'Response validity & relevance'!$T$3:$T$15)+0.5*SUMIF('Response validity & relevance'!$N$3:$N$15,"partial",'Response validity & relevance'!$T$3:$T$15) -> 0 | J17: =SUM('Response validity & relevance'!$T$3:$T$15)-SUMIF('Response validity & relevance'!$N$3:$N$15,"na",'Response validity & relevance'!$T$3:$T$15) -> 120
A18: Operations, ALM & adoption | B18: =IFERROR(ROUND(100*I18/J18,1),"n/a") -> 0 | C18: 6 | D18: =COUNTIF('Operations, ALM & adoption'!$N$3:$N$9,"pass") -> 0 | E18: =COUNTIF('Operations, ALM & adoption'!$N$3:$N$9,"partial") -> 0 | F18: =COUNTIF('Operations, ALM & adoption'!$N$3:$N$9,"fail") -> 0 | G18: =COUNTIF('Operations, ALM & adoption'!$N$3:$N$9,"na") -> 0 | H18: =COUNTIF('Operations, ALM & adoption'!$N$3:$N$9,"unknown") -> 7 | I18: =SUMIF('Operations, ALM & adoption'!$N$3:$N$9,"pass",'Operations, ALM & adoption'!$T$3:$T$9)+0.5*SUMIF('Operations, ALM & adoption'!$N$3:$N$9,"partial",'Operations, ALM & adoption'!$T$3:$T$9) -> 0 | J18: =SUM('Operations, ALM & adoption'!$T$3:$T$9)-SUMIF('Operations, ALM & adoption'!$N$3:$N$9,"na",'Operations, ALM & adoption'!$T$3:$T$9) -> 34
A20: OVERALL (weighted) | B20: =IFERROR(ROUND(SUMPRODUCT(B4:B18,C4:C18)/SUM(C4:C18),1),0) -> 0 | D20: =SUM(D4:D18) -> 0 | E20: =SUM(E4:E18) -> 0 | F20: =SUM(F4:F18) -> 0 | G20: =SUM(G4:G18) -> 0 | H20: =SUM(H4:H18) -> 138 | I20: =SUM(I4:I18) -> 0 | J20: =SUM(J4:J18) -> 836
A21: Blocker rules not met | B21: =IF(OR('Tenant & admin enablement'!N3="fail",'Tenant & admin enablement'!N3="unknown"),1,0)+IF(OR('Tenant & admin enablement'!N4="fail",'Tenant & admin enablement'!N4="unknown"),1,0)+IF(OR('Capacity, SKU, region & cost'!N3="fail",'Capacity, SKU, region & cost'!N3="unknown"),1,0)+IF(OR('Capacity, SKU, region & cost'!N4="fail",'Capacity, SKU, region & cost'!N4="unknown"),1,0)+IF(OR('AI data schema & scope reductio'!N3="fail",'AI data schema & scope reductio'!N3="unknown"),1,0)+IF(OR('Names, descriptions & linguisti'!N8="fail",'Names, descriptions & linguisti'!N8="unknown"),1,0)+IF(OR('Security, RLS & compliance'!N3="fail",'Security, RLS & compliance'!N3="unknown"),1,0)+IF(OR('Response validity & relevance'!N3="fail",'Response validity & relevance'!N3="unknown"),1,0) -> 8
A22: Maturity level | B22: =IF(B21>0,"Not Ready (GATED)",IF(B20<40,"Not Ready",IF(B20<60,"Foundational",IF(B20<75,"Operational",IF(B20<90,"Optimized","AI-Ready"))))) -> Not Ready (GATED)
A24: Gate rule | B24: Any blocker rule left at fail or unknown forces the maturity level to Not Ready, whatever the numeric score. There are 8 blocker rules in this pack.
A25: Bands | B25: Not Ready 0-39.99 | Foundational 40-59.99 | Operational 60-74.99 | Optimized 75-89.99 | AI-Ready 90-100

Sheet Tenant & admin enablement
A1: Tenant & admin enablement - 9 rules, area weight 10 | J1: Fill the yellow cells only. Result must be one of: unknown, pass, partial, fail, na
A2: Rule ID | B2: Title | C2: Severity | D2: Type | E2: Applies to | F2: Requirement | G2: Why it matters | H2: Hard limit | I2: How to check | J2: Remediation | K2: If not fixed | L2: Source | M2: Basis | N2: Result | O2: Evidence / link | P2: Owner | Q2: Due date | R2: Notes | T2: _weight
A3: TEN-001 | B3: Copilot / Azure OpenAI tenant switch is enabled for the intended audience | C3: blocker | D3: enablement | E3: copilot-powerbi, fabric-data-agent | F3: The tenant setting 'Users can use Copilot and other features powered by Azure OpenAI' must be enabled, scoped either to the whole organization or to the specific security groups that are in scope for AI. | G3: This is the master switch. Every downstream Copilot and data agent experience depends on it. | I3: (admin-portal) Fabric Admin Portal > Tenant settings > Copilot and Agent. Record state and the security groups it is scoped to. [expected: enabled] | J3: Enable the setting and scope it to the AI pilot security group rather than the entire organization, so that usage and capacity burn stay attributable during rollout. | K3: No Copilot or data agent functionality at all. | L3: Enable Fabric Copilot for Power BI; Copilot and Agent admin settings; Configure Fabric data agent tenant settings | M3: documented | N3: unknown | R3: Microsoft docs are inconsistent on the default state of this switch: the Copilot and Agent admin settings page and the Power BI enablement page describe it as enabled by default, while the data agent tenant settings page lists it as off. Do not assume - read the actual tenant state and record it as evidence. | T3: 13
A4: TEN-002 | B4: Cross-geo processing switch matches the capacity's region | C4: blocker | D4: enablement | E4: copilot-powerbi, fabric-data-agent | F4: If the Fabric capacity is outside the US regions and the EU Data Boundary, the tenant setting 'Data sent to Azure OpenAI can be processed outside your capacity's geographic region, compliance boundary, or national cloud instance' must be enabled, and that decision must be signed off by the data-residency owner. | G4: Azure OpenAI is deployed in US datacenters and the EU Data Boundary only. UK capacities route to the EU boundary; Australia, Brazil, Canada, India, Asia, Japan, Korea, South Africa, Southeast Asia and UAE route to the US. Without the switch, Copilot simply does not work in those regions. | I4: (admin-portal) Determine the capacity's region, then check the cross-geo processing tenant setting. Record both, plus the residency sign-off reference. [expected: enabled when capacity region is outside US and EU Data Boundary] | J4: Either enable cross-geo processing with documented residency approval, or relocate the capacity into a region where Azure OpenAI is served locally. | K4: Copilot requests fail in-region; users experience errors rather than degraded answers. | L4: Overview of Copilot in Fabric; Copilot and Agent admin settings | M4: documented | N4: unknown | T4: 13
A5: TEN-003 | B5: Cross-geo storage and conversation-history switches are a deliberate decision | C5: high | D5: governance | E5: fabric-data-agent, copilot-notebooks | F5: For tenants outside the EU Data Boundary and US, the settings 'Data sent to Azure OpenAI can be stored outside...' and 'Conversation history stored outside your capacity's geographic region...' must be explicitly decided - enabled with residency approval, or accepted as disabled with the loss of multi-session context understood. | G5: Conversation history is what gives agentic experiences memory across sessions; it is retained 28 days unless a user deletes it. Leaving these off outside EU/US silently degrades multi-turn quality. | H5: 28 days (hard) | I5: (admin-portal) Record both switch states and the documented decision. Both default to disabled. [expected: documented decision] | J5: Record the decision in the AI governance register. If disabled, set user expectations that each session starts cold. | K5: Agents lose cross-session context; users repeat themselves and blame the agent for forgetting. | L5: Copilot and Agent admin settings; Configure Fabric data agent tenant settings; Overview of Copilot in Fabric | M5: documented | N5: unknown | T5: 5
A6: TEN-004 | B6: 'Only show approved items in the standalone Copilot' is enabled once an approval process exists | C6: critical | D6: governance | E6: copilot-powerbi | F6: Once the organization has a working 'Approved for Copilot' review process, the tenant setting 'Only show approved items in the standalone Copilot in Power BI experience' should be enabled so standalone Copilot searches only curated content. | G6: This is the single most effective lever against the ad-hoc-scan behaviour: it stops standalone Copilot from ranging across every semantic model in the tenant and restricts it to models that have actually been prepared for AI. | I6: (admin-portal) Check the tenant setting state, and confirm at least one model has been marked Approved for Copilot. [expected: enabled] | J6: Stand up the approval review first (see WSP-004), then flip this switch. Enabling it with zero approved items makes standalone Copilot return nothing. | K6: Standalone Copilot searches unprepared models and produces confident answers from models nobody has validated. | L6: Copilot and Agent admin settings; Enable Fabric Copilot for Power BI | M6: documented | N6: unknown | T6: 8
A7: TEN-005 | B7: Standalone Copilot experience switch state is intentional | C7: high | D7: governance | E7: copilot-powerbi | F7: The setting 'Users can access a standalone, cross-item Copilot in Power BI experience' must be explicitly set on or off with a recorded rationale, not left at whatever the default happens to be. | G7: Standalone Copilot has the broadest blast radius of any Copilot surface because it is not anchored to one report. It also depends on the parent Azure OpenAI switch and is unavailable in Spain Central, Qatar, India-West and Mexico. | I7: (admin-portal) Record switch state, target groups, and the rationale. Confirm the tenant home region is not one of the unsupported regions. [expected: documented decision] | J7: Keep it off until model preparation and approval reach Optimized maturity, then enable narrowly. | K7: Broad, ungrounded question surface exposed before models are ready. | L7: Copilot and Agent admin settings; Prepare your data for AI to improve Copilot results (preview) | M7: documented | N7: unknown | T7: 5
A8: TEN-006 | B8: Fabric Copilot capacity designation is configured for cost attribution | C8: high | D8: governance | E8: copilot-powerbi, fabric-data-agent | F8: If Copilot cost needs to be isolated from analytical workloads, the setting 'Capacities can be designated as Copilot in Fabric capacities' must be enabled and a dedicated Copilot capacity assigned. | G8: Copilot consumes the same CU pool as everything else. A dedicated Copilot capacity consolidates AI billing and prevents AI spikes from throttling refreshes and report queries. | I8: (admin-portal) Check the tenant setting, then check whether a capacity is designated and which users or groups are assigned to it. [expected: designated capacity or documented decision not to] | J8: Designate a Copilot capacity and assign the AI audience to it, so AI Query operations are separately visible in the Capacity Metrics app. | K8: AI consumption is indistinguishable from BI consumption; throttling incidents cannot be attributed. | L8: Copilot and Agent admin settings; Configure Fabric data agent tenant settings; Enable Fabric Copilot for Power BI | M8: documented | N8: unknown | T8: 5
A9: TEN-007 | B9: Capacity-level Copilot delegation is reviewed, not just tenant settings | C9: high | D9: governance | E9: copilot-powerbi, fabric-data-agent | F9: Delegated tenant settings on each in-scope capacity must be reviewed, because a capacity administrator can enable Copilot at capacity level even where it is disabled at tenant level. | G9: Reviewing only the tenant page gives a false sense of control. Cross-geo delegation notably does not auto-delegate and must be set per capacity. | I9: (admin-portal) Admin Portal > Capacity settings > each capacity > Delegated tenant settings. Record any capacity that overrides the tenant position. [expected: per-capacity review record] | J9: Audit every capacity's delegated settings and reconcile overrides against the intended tenant policy. | K9: Shadow Copilot enablement on capacities the AI governance team does not know about. | L9: Enable Fabric Copilot for Power BI | M9: documented | N9: unknown | T9: 5
A10: TEN-008 | B10: Purview DLP and access-restriction policies are evaluated for AI surfaces | C10: critical | D10: governance | E10: fabric-data-agent | F10: Where the tenant is governed by Microsoft Purview, DLP policies for Fabric Data Warehouse and access-restriction policies for KQL Database, SQL Database and Data Warehouse must be reviewed against the data an agent can reach. | G10: An agent inherits the user's read access; Purview policies are the layer that prevents an otherwise-authorized query from surfacing regulated content in a chat response. | I10: (manual) List agent data sources, then confirm each has been assessed against active Purview DLP and access-restriction policies. [expected: assessment record per data source] | J10: Run a Purview policy review as part of agent intake; block sources that carry regulated data without a policy. | K10: Regulated data surfaced conversationally with no DLP interception. | L10: Fabric data agent creation | M10: documented | N10: unknown | T10: 8
A11: TEN-009 | B11: Tenant setting changes are allowed an hour to propagate before troubleshooting | C11: low | D11: governance | E11: copilot-powerbi, fabric-data-agent | F11: The runbook must state that Copilot and data agent tenant settings can take up to one hour to take effect, and that troubleshooting should not begin before that window elapses. | G11: Most 'Copilot is broken after we enabled it' escalations are impatience. Codifying the wait prevents wasted support cycles and premature setting churn. | H11: 1 hours (soft) | I11: (manual) Confirm the enablement runbook documents the propagation delay. [expected: documented in runbook] | J11: Add the one-hour propagation note to the enablement runbook and the support script. | K11: Settings toggled repeatedly during the propagation window, confusing the audit trail. | L11: Configure Fabric data agent tenant settings | M11: documented | N11: unknown | T11: 1

Sheet Capacity, SKU, region & cost
A1: Capacity, SKU, region & cost - 6 rules, area weight 10 | J1: Fill the yellow cells only. Result must be one of: unknown, pass, partial, fail, na
A2: Rule ID | B2: Title | C2: Severity | D2: Type | E2: Applies to | F2: Requirement | G2: Why it matters | H2: Hard limit | I2: How to check | J2: Remediation | K2: If not fixed | L2: Source | M2: Basis | N2: Result | O2: Evidence / link | P2: Owner | Q2: Due date | R2: Notes | T2: _weight
A3: CAP-001 | B3: Capacity meets the minimum paid SKU | C3: blocker | D3: limit | E3: copilot-powerbi, fabric-data-agent | F3: Every workspace hosting a Copilot-enabled model or a data agent must be on a paid Fabric capacity of F2 or higher, or Power BI Premium P1 or higher with Fabric enabled. | G3: Trial SKUs are not supported for Azure OpenAI access. This is a hard gate, not a performance recommendation. | H3: F2 / P1 sku (hard) | I3: (api) Enumerate in-scope workspaces and their assigned capacity SKU. Flag any on trial, PPU-only, or shared capacity. [gte F2] | J3: Move the workspace to a qualifying paid capacity, or assign users to a Fabric Copilot capacity. | K3: Copilot and data agent features are unavailable regardless of tenant settings. | L3: Fabric data agent creation; Overview of Copilot in Fabric; Use Copilot with semantic models in Power BI | M3: documented | N3: unknown | T3: 13
A4: CAP-002 | B4: Capacity region is supported and consistent across agent and sources | C4: blocker | D4: limit | E4: fabric-data-agent | F4: The data agent's workspace capacity and every data source workspace capacity must be in the same region, and that region must be one where Fabric AI workloads are available. | G4: Cross-region source binding fails outright - a Lakehouse on North Europe capacity will not serve an agent whose capacity is in France Central. Sovereign clouds are not supported at all. | I4: (api) For each agent, list the region of its own capacity and of every bound data source's capacity. All must match. [expected: identical region across agent and all sources] | J4: Relocate either the agent workspace or the source workspaces so all sit on same-region capacity. | K4: Agent creation or query execution fails against the mismatched source. | L4: Fabric data agent creation; Overview of Copilot in Fabric | M4: documented | N4: unknown | T4: 13
A5: CAP-003 | B5: AI Query consumption is monitored in the Capacity Metrics app | C5: critical | D5: performance | E5: fabric-data-agent, copilot-powerbi | F5: AI Query operations and the LlmPlugin item kind must be actively monitored in the Fabric Capacity Metrics app, with a named owner and a review cadence. | G5: Data agent requests bill at 100 CU seconds per 1,000 input tokens, 10 CU seconds per 1,000 cached input tokens, and 400 CU seconds per 1,000 output tokens - and the generated SQL/DAX/KQL is billed separately to its own engine on top. Without monitoring, a verbose instruction set silently multiplies cost on every single question. | H5: inputPer1kTokens=100; cachedInputPer1kTokens=10; outputPer1kTokens=400 CU seconds (hard) | I5: (metrics) Capacity Metrics app, filter to AI Query operations and the LlmPlugin item kind. Confirm a monitoring owner and cadence exist. [expected: monitored with named owner] | J5: Add AI Query to the capacity review pack; alert on week-over-week growth and on the ratio of output to input tokens. | K5: Unbounded AI spend and eventual capacity-wide throttling that takes refreshes down with it. | L5: Data agent consumption | M5: documented | N5: unknown | T5: 8
A6: CAP-004 | B6: Throttling risk from AI workloads is assessed against the SKU | C6: high | D6: performance | E6: fabric-data-agent, copilot-powerbi | F6: Expected peak AI request volume must be modelled against the capacity's daily CU budget, and the result recorded, before broad rollout. | G6: Data agent operations run as background jobs which smooth peaks, but once capacity is exhausted all operations shut down - not just AI. An F64 carrying 1,536 CU hours per day supports on the order of 13,800 requests per day before exhaustion; that number falls fast as instructions and conversation history grow. | I6: (manual) Record the SKU, its daily CU hours, the modelled average tokens per request, and the derived request ceiling. Compare against forecast adoption. [expected: documented headroom model] | J6: Model it explicitly, then either size the capacity for the forecast or cap the audience until instruction and schema trimming brings per-request tokens down. | K6: AI adoption success takes down unrelated Fabric workloads on the same capacity. | L6: Data agent consumption | M6: documented | N6: unknown | T6: 5
A7: CAP-005 | B7: Private Link and closed-network constraints are checked | C7: critical | D7: limit | E7: copilot-powerbi, fabric-data-agent | F7: Confirm that in-scope capacities do not depend on Private Link or closed-network configurations that are unsupported for Copilot. | G7: Copilot is not supported behind Private Link or closed networks. Discovering this after a rollout announcement is expensive. | I7: (admin-portal) Check tenant and workspace networking configuration for Private Link / closed-network enforcement. [expected: not enforced for AI-enabled workspaces] | J7: Carve the AI-enabled workspaces out of the Private Link enforcement scope, or accept that Copilot is unavailable there. | K7: Copilot silently unavailable despite every switch appearing correct. | L7: Enable Fabric Copilot for Power BI | M7: documented | N7: unknown | T7: 8
A8: CAP-006 | B8: Workspace outbound access protection boundaries are understood for agents | C8: medium | D8: governance | E8: fabric-data-agent | F8: Where workspace outbound access protection is in force, the permitted external endpoints must be documented and confirmed sufficient for the agent's data sources. | G8: Agents operate inside the workspace outbound access protection boundary; an administrator's endpoint allowlist directly determines what the agent can reach. | I8: (manual) Record outbound access protection state and the allowlisted endpoints for each agent workspace. [expected: documented] | J8: Reconcile the endpoint allowlist with the agent's bound sources before go-live. | K8: Intermittent, hard-to-diagnose source failures. | L8: Fabric data agent creation | M8: documented | N8: unknown | T8: 3

Sheet Workspace & item governance
A1: Workspace & item governance - 7 rules, area weight 6 | J1: Fill the yellow cells only. Result must be one of: unknown, pass, partial, fail, na
A2: Rule ID | B2: Title | C2: Severity | D2: Type | E2: Applies to | F2: Requirement | G2: Why it matters | H2: Hard limit | I2: How to check | J2: Remediation | K2: If not fixed | L2: Source | M2: Basis | N2: Result | O2: Evidence / link | P2: Owner | Q2: Due date | R2: Notes | T2: _weight
A3: WSP-001 | B3: AI-enabled workspaces are an explicit, enumerated set | C3: critical | D3: governance | E3: copilot-powerbi, fabric-data-agent | F3: There must be a maintained register of which workspaces are in scope for Copilot and data agents, rather than AI being implicitly available wherever capacity happens to be assigned. | G3: Scope control is the foundation of every other rule in this pack. You cannot tune what you have not bounded. | I3: (manual) Confirm a register exists, is current within the last quarter, and names an owner per workspace. [expected: current register] | J3: Publish the register and review it at each capacity review. | K3: AI surface expands invisibly; assessment results go stale immediately. | L3: Established semantic modeling / Copilot tuning practice (not a single Microsoft doc) | M3: inferred | N3: unknown | T3: 8
A4: WSP-002 | B4: Copilot cannot be enabled per workload - the audience decision is all-or-nothing | C4: high | D4: governance | E4: copilot-powerbi, fabric-data-agent | F4: The rollout plan must account for the fact that enabling Copilot in a capacity for a user or security group grants that group all Copilot workloads and experiences; it cannot be enabled for one experience only. | G4: Teams frequently plan a 'Copilot for Power BI only' pilot that is not technically achievable. The control point is the audience, not the workload. | I4: (manual) Confirm the rollout plan controls exposure by security group and capacity assignment, not by workload selection. [expected: audience-based scoping] | J4: Rewrite the rollout plan around security groups and dedicated capacities. | K4: Users reach Copilot experiences over unprepared workloads that were never in the pilot scope. | L4: Use Copilot with semantic models in Power BI | M4: documented | N4: unknown | T4: 5
A5: WSP-003 | B5: Staging, development and sandbox workspaces are excluded from AI capacity | C5: high | D5: governance | E5: copilot-powerbi | F5: Development, staging and personal sandbox workspaces must not sit on capacity where Copilot is enabled for business users. | G5: Half-built models with placeholder measures and unhidden technical columns are exactly the content that teaches users not to trust Copilot. | I5: (api) Cross-reference the workspace register against capacity assignment; flag any dev/test workspace on a Copilot-enabled capacity accessible to business users. [expected: no dev/test workspaces exposed] | J5: Move non-production workspaces to a separate capacity or restrict the Copilot security group to production workspace members. | K5: Users get answers from unfinished models and lose confidence permanently. | L5: Established semantic modeling / Copilot tuning practice (not a single Microsoft doc); Best practices for configuring your data agent | M5: inferred | N5: unknown | T5: 5
A6: WSP-004 | B6: 'Approved for Copilot' is applied through a real review, not by default | C6: critical | D6: governance | E6: copilot-powerbi | F6: Every semantic model marked 'Approved for Copilot' must have passed a documented review covering schema scoping, descriptions, verified answers and a golden-question test pass. | G6: Approval is the trust signal shown to users; unapproved models display a warning advising users to inspect results and contact the owner. Rubber-stamping approval destroys the signal's value. | I6: (manual) For each approved model, confirm a review record exists with a date, reviewer, and golden-question pass rate. [expected: review record per approved model] | J6: Define the approval checklist from this rule pack and gate the flag behind it. | K6: The approval badge becomes noise and users cannot tell prepared models from unprepared ones. | L6: Copilot in Power BI tutorial: prepare a semantic model for AI; Copilot and Agent admin settings | M6: documented | N6: unknown | T6: 8
A7: WSP-005 | B7: Reports, dashboards and apps cannot be approved - only semantic models | C7: low | D7: limit | E7: copilot-powerbi | F7: Governance documentation must state that there is currently no way to mark a report, dashboard or app as approved for Copilot; only semantic models carry the flag. | G7: Teams design approval workflows around reports and then find the flag does not exist, leaving the process half-implemented. | I7: (manual) Confirm the governance doc reflects the model-only scope of approval. [expected: documented] | J7: Anchor the approval process on semantic models and treat report quality as a separate control. | K7: Approval process design churn. | L7: Prepare your data for AI to improve Copilot results (preview) | M7: documented | N7: unknown | T7: 1
A8: WSP-006 | B8: Semantic model description is populated for discovery | C8: high | D8: metadata | E8: copilot-powerbi | F8: Each in-scope semantic model must have a populated description in model settings that names the subject areas, key entities and the questions it is meant to answer. | G8: Descriptions feed the Search grounding path, which is how standalone Copilot decides which model to use for a question. A blank description makes the model effectively invisible or, worse, picked at random. | I8: (api) Read the model description for every in-scope model; flag empty, default, or single-word values. [expected: non-empty, keyword-rich description] | J8: Write a description covering tables, measures, relationships and intended audience, using distinct keywords rather than generic phrasing. | K8: Standalone Copilot routes questions to the wrong model. | L8: Copilot in Power BI tutorial: prepare a semantic model for AI; Frequently asked questions about preparing data for AI | M8: documented | N8: unknown | T8: 5
A9: WSP-007 | B9: Report descriptions are populated where reports are part of the AI surface | C9: medium | D9: metadata | E9: copilot-powerbi | F9: Reports exposed to Copilot should carry a description in File > Settings that provides natural-language context for data discovery. | G9: Report descriptions contribute to discovery and to the report summary experience. | I9: (manual) Sample in-scope reports and check for a populated description. [expected: non-empty description] | J9: Add a one-to-two sentence description naming the analysis and its dimensions. | K9: Weaker discovery and less useful report summaries. | L9: Copilot in Power BI tutorial: prepare a semantic model for AI | M9: documented | N9: unknown | T9: 3

Sheet AI data schema & scope reductio
A1: AI data schema & scope reduction - 21 rules, area weight 14 | J1: Fill the yellow cells only. Result must be one of: unknown, pass, partial, fail, na
A2: Rule ID | B2: Title | C2: Severity | D2: Type | E2: Applies to | F2: Requirement | G2: Why it matters | H2: Hard limit | I2: How to check | J2: Remediation | K2: If not fixed | L2: Source | M2: Basis | N2: Result | O2: Evidence / link | P2: Owner | Q2: Due date | R2: Notes | T2: _weight
A3: SCH-001 | B3: An AI data schema is explicitly defined for every in-scope semantic model | C3: blocker | D3: config | E3: copilot-powerbi, fabric-data-agent | F3: Every semantic model exposed to Copilot or bound to a data agent must have an AI data schema defined through Prep data for AI, rather than defaulting to the full model surface. | G3: This is the primary control against the ad-hoc-SQL-server behaviour. The DAX generation tool uses only the AI data schema. If you never define one, the generator reasons over everything you own. | I3: (tmdl) Inspect the model's LSDL / AI data schema definition. Confirm a curated selection exists and is narrower than the full object list. [expected: defined and narrower than full model] | J3: Open Prep data for AI > Simplify the data schema and deselect every field not required by the intended question set. | K3: The generator considers every table, column and measure on every question - maximum latency, maximum token cost, maximum ambiguity. | L3: Copilot in Power BI tutorial: prepare a semantic model for AI; Semantic model best practices for data agent; Prepare your data for AI to improve Copilot results (preview) | M3: documented | N3: unknown | T3: 13
A4: SCH-002 | B4: Model entity count stays within the 1,000-entity indexing ceiling | C4: critical | D4: limit | E4: copilot-powerbi, fabric-data-agent | F4: The combined count of tables and columns in the model should stay at or below 1,000 entities, or the AI data schema must reduce the exposed surface to below that ceiling. | G4: Power BI indexes a maximum of 1,000 model entities (tables and columns combined) for instance-value search. Beyond that, columns go unindexed and value-based filtering silently degrades. | H4: 1000 entities (tables + columns) (hard) | I4: (dax) Count tables plus columns via INFO.TABLES()/INFO.COLUMNS() or a VPAX extract. Compare against 1000. [lte 1000 entities] | J4: Trim the model, or narrow the AI data schema so the AI-visible entity count is well under the ceiling. Aim materially below 1,000, not at it. | K4: Columns are skipped during indexing; Copilot cannot resolve filter values it should be able to find. | L4: Frequently asked questions about preparing data for AI | M4: documented | N4: unknown | T4: 8
A5: SCH-003 | B5: Instance-value indexing stays within the 5 million value ceiling | C5: critical | D5: limit | E5: copilot-powerbi | F5: The total indexed instance values across the model must stay under 5 million, and high-cardinality columns must be excluded from the AI data schema where they are not needed for filtering. | G5: Indexing stops at 5 million instance values. When the next column would push the total over, Power BI skips that column entirely - and it may be a column that matters. A single high-cardinality key can consume the budget and starve every column after it. | H5: 5000000 instance values (hard) | I5: (dax) Estimate distinct-value counts per AI-visible column (APPROXIMATEDISTINCTCOUNT or COLUMNSTATISTICS) and sum. Compare against 5,000,000. [lte 5000000 instance values] | J5: Deselect surrogate keys, GUIDs, free-text notes and transaction identifiers from the AI data schema. Keep the columns users actually name in questions. | K5: Arbitrary columns silently unindexed; value filters fail unpredictably and look like model bugs. | L5: Frequently asked questions about preparing data for AI | M5: documented | N5: unknown | T5: 8
A6: SCH-004 | B6: Filterable text values are under 100 characters | C6: high | D6: limit | E6: copilot-powerbi | F6: Columns intended for value-based filtering by Copilot must contain values shorter than 100 characters. | G6: Text values of 100 characters or more are not indexed. Long descriptive strings will never be matched by a user's natural-language filter no matter how the question is phrased. | H6: 100 characters (hard) | I6: (dax) For each AI-visible text column, compute MAX(LEN(column)). Flag any column used for filtering whose values reach 100 characters. [lt 100 characters] | J6: Split long text into a short filterable code or category column plus a long descriptive column, and expose only the short one to the AI data schema. | K6: Users filter on a value that visibly exists in the report and Copilot insists it cannot find it. | L6: Frequently asked questions about preparing data for AI | M6: documented | N6: unknown | T6: 5
A7: SCH-005 | B7: Copilot Diagnostics shows no AgentSchemaReduced warning | C7: critical | D7: validation | E7: copilot-powerbi | F7: Copilot Diagnostics must not report 'AgentSchemaReduced' for in-scope models under representative questions. | G7: AgentSchemaReduced means the schema was too large for Copilot to render and Copilot automatically cut it down - by its own choice, not yours. Whatever it dropped is invisible to the generator and you did not decide what went. | I7: (manual) Run the golden question set and inspect Copilot Diagnostics warnings for AgentSchemaReduced. [expected: warning absent] | J7: Reduce the AI data schema yourself until the warning clears, so schema reduction is a deliberate curation decision rather than an automatic truncation. | K7: Silent, uncontrolled loss of schema; answers omit data that exists and nobody can explain why. | L7: Frequently asked questions about preparing data for AI | M7: documented | N7: unknown | T7: 8
A8: SCH-006 | B8: Surrogate keys and relationship identifiers are removed from the AI schema | C8: high | D8: modeling | E8: copilot-powerbi, fabric-data-agent | F8: Unique identifier columns used only to define relationships must be deselected from the AI data schema. | G8: Documented explicitly as a field type to deselect. Keys carry no business meaning, add cardinality against the indexing budget, and invite the generator to join or group on them. | I8: (tmdl) List AI-visible columns whose names match key patterns (ID, Key, SK, GUID, Code suffixes) and confirm exclusion unless deliberately kept. [expected: excluded] | J8: Deselect them in Simplify the data schema. Relationships still work; the generator just stops seeing the keys. | K8: Grouping by meaningless identifiers, wasted index budget, and joins the generator invents rather than follows. | L8: Copilot in Power BI tutorial: prepare a semantic model for AI; Best practices for configuring your data agent | M8: documented | N8: unknown | T8: 5
A9: SCH-007 | B9: Sort-order and helper columns are removed from the AI schema | C9: high | D9: modeling | E9: copilot-powerbi | F9: Sort-by columns such as Month (Sort Order) or Day (Sort Order), and other presentation helper columns, must be deselected from the AI data schema. | G9: Called out explicitly as fields to deselect. They duplicate a real attribute in numeric form, so the generator has two plausible columns for one concept and picks wrong roughly half the time. | I9: (tmdl) Identify columns used as Sort By Column targets and confirm they are excluded from the AI schema. [expected: excluded] | J9: Deselect all sort-order columns. Sorting behaviour in visuals is unaffected. | K9: Answers grouped by 1..12 instead of month names; user trust erodes on cosmetic-looking errors. | L9: Copilot in Power BI tutorial: prepare a semantic model for AI | M9: documented | N9: unknown | T9: 5
A10: SCH-008 | B10: Archived, staging and audit tables are excluded | C10: high | D10: modeling | E10: copilot-powerbi, fabric-data-agent | F10: Archived, staging, audit and unrelated tables must be excluded from both the AI data schema and any data agent object selection. | G10: Explicit guidance for data agent configuration: select only the tables, columns, views and functions needed for the intended questions. Staging tables are the classic source of near-duplicate results. | I10: (manual) Review the AI-visible table list against the intended question set; flag any table that no in-scope question needs. [expected: excluded] | J10: Remove them from selection. If they must stay in the model for lineage, hide them and exclude them from the AI schema. | K10: The generator queries a staging copy and returns numbers that do not tie to any published report. | L10: Best practices for configuring your data agent | M10: documented | N10: unknown | T10: 5
A11: SCH-009 | B11: AI data schema is scoped to a declared question set | C11: critical | D11: governance | E11: copilot-powerbi, fabric-data-agent | F11: Each AI data schema must be traceable to a written statement of the question scope the model is meant to serve, and every included object must be justified by at least one question in that scope. | G11: 'Select only relevant objects based on the data agent's question scope to reduce ambiguity and latency.' Without a declared scope, inclusion decisions are arbitrary and the schema only ever grows. | I11: (manual) Confirm a question-scope document exists per model/agent and that schema inclusions map to it. [expected: documented question scope] | J11: Write the scope statement first, derive the schema from it, and reject additions that no scoped question requires. | K11: Schema sprawl returns within two release cycles and undoes every other tuning effort. | L11: Semantic model best practices for data agent; Best practices for configuring your data agent | M11: documented | N11: unknown | T11: 8
A12: SCH-010 | B12: Data agent object selection matches the model's AI data schema | C12: critical | D12: config | E12: fabric-data-agent | F12: For a semantic model bound to a data agent, the tables selected in the data agent must be the same tables defined in the model's Prep for AI AI data schema. | G12: Stated as a direct consistency rule. Divergence means the agent exposes objects the DAX generator was never configured to reason about. | I12: (manual) Diff the agent's selected object list against the model's AI data schema. The sets must match. [expected: identical object sets] | J12: Reconcile the two selections and add a check to the release process so they cannot drift. | K12: Objects visible to the agent but absent from the generation schema produce failed or nonsensical DAX. | L12: Semantic model best practices for data agent | M12: documented | N12: unknown | T12: 8
A13: SCH-011 | B13: Dependent objects of selected measures are included in the schema | C13: critical | D13: config | E13: copilot-powerbi, fabric-data-agent | F13: When a measure is included in the AI data schema, every object it depends on must also be included. | G13: Explicit dependency rule; Semantic Link Labs' get_measure_dependencies is the recommended way to enumerate them. A measure whose dependencies were trimmed away fails at query time. | I13: (api) Run get_measure_dependencies (Semantic Link Labs) across AI-visible measures and confirm every dependency is also AI-visible. [expected: all dependencies present] | J13: Add the missing dependencies, or drop the measure from the schema if its dependencies must stay hidden. | K13: Generated DAX references objects the generator believes exist and the query errors. | L13: Semantic model best practices for data agent | M13: documented | N13: unknown | T13: 8
A14: SCH-012 | B14: Hidden fields are not silently relied upon | C14: critical | D14: config | E14: copilot-powerbi, fabric-data-agent | F14: Any field that Copilot must be able to use has to be visible; hidden measures and columns are excluded from grounding and must not appear in verified answers. | G14: Hidden fields are excluded from grounding data, and verified answers referencing hidden columns simply do not work. Teams routinely hide a column for report tidiness and then wonder why Copilot cannot answer about it. | I14: (dax) List objects referenced by verified answers and by the question scope, and confirm none are hidden. [expected: no hidden objects in AI scope] | J14: Unhide the fields Copilot needs, or rewrite the verified answer against visible equivalents. | K14: Verified answers fail silently and Copilot claims data it can see in reports does not exist. | L14: Use Copilot with semantic models in Power BI; Semantic model best practices for data agent | M14: documented | N14: unknown | T14: 8
A15: SCH-013 | B15: Private tables are understood to be entirely invisible to Copilot | C15: high | D15: config | E15: copilot-powerbi | F15: Tables marked private must be documented as fully excluded from all Copilot grounding, and no AI capability may depend on them. | G15: Copilot ignores private tables entirely across both the data-question and DAX query view paths. This is a useful deliberate exclusion mechanism, but a trap when unintentional. | I15: (tmdl) List tables marked private and confirm no in-scope question depends on them. [expected: documented and no dependency] | J15: Use the private flag deliberately to fence off sensitive or technical tables; unmark any table Copilot legitimately needs. | K15: Unexplainable gaps in Copilot's knowledge of the model. | L15: Use Copilot with semantic models in Power BI | M15: documented | N15: unknown | T15: 5
A16: SCH-014 | B16: Duplicate field names across tables are eliminated or disambiguated | C16: high | D16: modeling | E16: copilot-powerbi, fabric-data-agent | F16: The AI-visible schema must not contain identically named fields in multiple tables unless each carries a description that distinguishes it. | G16: Called out directly: 'Name' in a Customer table versus a Store table forces the generator to guess. Ambiguity at schema level cannot be recovered by a better prompt. | I16: (dax) Group AI-visible column and measure names; flag any name appearing in more than one table. [equals 0] | J16: Rename to Customer Name / Store Name, or add distinguishing descriptions to each. | K16: Roughly random field selection on any question naming the ambiguous term. | L16: Copilot in Power BI tutorial: prepare a semantic model for AI; Semantic model best practices for data agent | M16: documented | N16: unknown | T16: 5
A17: SCH-015 | B17: Instance-value reindexing cadence is understood and accounted for | C17: medium | D17: performance | E17: copilot-powerbi | F17: The team must document the reindexing behaviour that applies to each model type and set user expectations accordingly. | G17: Import models reindex on manual or scheduled refresh, but only when Copilot or Q&A has been used in the last 14 days. DirectQuery and Direct Lake reindex when the index is older than 24 hours under the same 14-day activity condition, with COLUMNSTATISTICS cached for 7 days. A model nobody has asked a question of for two weeks stops being reindexed. | H17: activityWindowDays=14; directQueryReindexHours=24; columnStatisticsCacheDays=7; firstIndexMinutes=15 mixed (hard) | I17: (manual) Confirm the operations runbook records the reindexing rules per model type and the 14-day activity dependency. [expected: documented] | J17: Document it, and for low-traffic but important models schedule a periodic synthetic question to keep the model within the activity window. | K17: Stale instance values produce filter misses that look like data errors. | L17: Frequently asked questions about preparing data for AI | M17: documented | N17: unknown | T17: 3
A18: SCH-016 | B18: DirectQuery indexing constraints are accepted or mitigated | C18: medium | D18: limit | E18: copilot-powerbi | F18: For DirectQuery models, confirm the source supports APPROXIMATEDISTINCTCOUNT and accept that indexing occurs at most once per 24 hours unless the model is republished. | G18: Only columns from sources supporting APPROXIMATEDISTINCTCOUNT are indexed at all. A failed underlying refresh leaves a stale index until the next successful one. | I18: (manual) For each DirectQuery model, record source support for APPROXIMATEDISTINCTCOUNT and the observed index age. [expected: documented] | J18: Where the source does not support it, consider Import or Direct Lake for the AI-facing model. | K18: Value filtering effectively unavailable on DirectQuery models against unsupported sources. | L18: Frequently asked questions about preparing data for AI | M18: documented | N18: unknown | T18: 3
A19: SCH-017 | B19: Prep for AI changes are given time to propagate before re-testing | C19: low | D19: operations | E19: copilot-powerbi | F19: Test cycles must allow up to 24 hours for Prep for AI changes to affect Copilot results, typically within an hour, with the longer tail on models that have many attached reports. | G19: Re-testing five minutes after a change and concluding the change did nothing leads to thrashing the configuration. | H19: 24 hours (soft) | I19: (manual) Confirm the test procedure documents the propagation window. [expected: documented] | J19: Build the wait into the evaluation cadence; batch configuration changes rather than tuning one setting at a time. | K19: Configuration churn and false conclusions about which settings help. | L19: Prepare your data for AI to improve Copilot results (preview) | M19: documented | N19: unknown | T19: 1
A20: SCH-018 | B20: Prep for AI edits deployed via Git or pipelines are followed by a refresh | C20: high | D20: operations | E20: copilot-powerbi | F20: After deploying LSDL or Prep for AI changes through Git integration or deployment pipelines, the model must be refreshed in the Power BI service to sync the changes. | G20: Explicit requirement. Import models must be refreshed; DirectQuery and Direct Lake models must be refreshed but only once a day. Skipping this leaves production running the previous AI configuration while source control says otherwise. | I20: (manual) Confirm the deployment pipeline includes a post-deployment refresh step for AI-configured models. [expected: refresh step present] | J20: Add the refresh to the release pipeline and verify the AI configuration post-deployment rather than assuming it landed. | K20: Deployed AI configuration silently inactive in production. | L20: Prepare your data for AI to improve Copilot results (preview) | M20: documented | N20: unknown | T20: 5
A21: SCH-019 | B21: Connection type is supported for Desktop-based Prep for AI authoring | C21: medium | D21: limit | E21: copilot-powerbi | F21: Where Prep for AI is authored in Power BI Desktop, the model must use Import, DirectQuery or local Composite mode. | G21: Power BI Desktop supports only those connection types for Prep data for AI. All model types can use the features in the Power BI service, so the constraint is on where you author, not where you consume. | I21: (manual) Record the connection type of each model and where its AI configuration is authored. | J21: Author Prep for AI in the service for model types Desktop does not support. | K21: Prep for AI unavailable in Desktop and the team assumes the feature is broken. | L21: Prepare your data for AI to improve Copilot results (preview) | M21: documented | N21: unknown | T21: 3
A22: SCH-020 | B22: Data agent stays within the five data source limit and uses the minimum needed | C22: critical | D22: limit | E22: fabric-data-agent | F22: A data agent must be bound to no more than five data sources, and to the fewest sources that its question scope actually requires. | G22: Five sources is a hard cap in any combination across Lakehouses, Warehouses, semantic models, KQL databases, mirrored databases, ontologies and Microsoft Graph. Every additional source widens the routing decision the agent has to make on every question. | H22: 5 data sources per agent (hard) | I22: (api) Count bound data sources per agent and compare against the intended question scope. [lte 5 data sources] | J22: Split broad agents into several narrowly scoped agents rather than binding more sources to one. | K22: At the cap, source routing errors dominate; beyond it, configuration is rejected. | L22: Fabric data agent creation | M22: documented | N22: unknown | T22: 8
A23: SCH-021 | B23: Lakehouse content is exposed as tables, not files | C23: high | D23: limit | E23: fabric-data-agent | F23: Data intended for agent consumption from a Lakehouse must be registered as tables; standalone files are not accessible. | G23: Agents access only Lakehouse tables, not standalone CSV or JSON files unless those are ingested as tables. Unstructured formats such as .pdf, .docx and .txt are unsupported outright. | I23: (manual) For each Lakehouse source, confirm the required data is registered as tables. [expected: tables registered] | J23: Ingest the files as Delta tables before binding the Lakehouse to the agent. | K23: The agent cannot see data the user can see in OneLake. | L23: Fabric data agent creation | M23: documented | N23: unknown | T23: 5

Sheet Semantic model structure
A1: Semantic model structure - 10 rules, area weight 12 | J1: Fill the yellow cells only. Result must be one of: unknown, pass, partial, fail, na
A2: Rule ID | B2: Title | C2: Severity | D2: Type | E2: Applies to | F2: Requirement | G2: Why it matters | H2: Hard limit | I2: How to check | J2: Remediation | K2: If not fixed | L2: Source | M2: Basis | N2: Result | O2: Evidence / link | P2: Owner | Q2: Due date | R2: Notes | T2: _weight
A3: MOD-001 | B3: Model follows a star schema with distinct fact and dimension tables | C3: critical | D3: modeling | E3: copilot-powerbi, fabric-data-agent | F3: AI-facing semantic models must use a star schema with clearly separated fact and dimension tables; flat denormalized tables and pivoted structures must be avoided. | G3: Named as the primary structural pitfall: non-star schemas make efficient DAX harder to write correctly, so the generator produces inefficient or wrong queries. This is the single largest structural driver of the broad-scan behaviour. | I3: (tmdl) Review the relationship graph. Flag snowflaked chains, fact-to-fact relationships, and wide flat tables carrying both measures and descriptive attributes. [expected: star schema] | J3: Refactor into conformed dimensions and narrow fact tables. Unpivot wide tables so each row is one observation. | K3: Inefficient generated DAX, longer scans, higher CU burn per question, and lower answer accuracy. | L3: Semantic model best practices for data agent; Optimize your semantic model for Copilot in Power BI; Use Copilot with semantic models in Power BI | M3: documented | N3: unknown | T3: 8
A4: MOD-002 | B4: Relationships are defined with explicit, correct cardinality | C4: critical | D4: modeling | E4: copilot-powerbi, fabric-data-agent | F4: Every relationship between AI-visible tables must exist and declare the correct cardinality - one-to-many, many-to-one, or many-to-many - and the correct filter direction. | G4: Clear relationships with specified cardinality are a stated requirement. Missing or wrong relationships force the generator to invent joins, which is where fabricated numbers come from. | I4: (dax) Enumerate relationships via INFO.RELATIONSHIPS(). Flag missing joins between AI-visible fact and dimension tables, and any many-to-many not deliberately intended. [expected: complete, correctly typed relationships] | J4: Define the missing relationships and correct cardinality. Replace incidental many-to-many with a bridge dimension. | K4: Cross-joins, inflated totals, and answers that cannot be reconciled to any report. | L4: Optimize your semantic model for Copilot in Power BI | M4: documented | N4: unknown | T4: 8
A5: MOD-003 | B5: Ambiguous relationship paths are eliminated | C5: high | D5: modeling | E5: copilot-powerbi, fabric-data-agent | F5: The model must not contain ambiguous relationship paths between AI-visible tables. | G5: Explicitly listed among the practices to follow. Where two paths connect the same tables, the generator's choice is not predictable and neither are the results. | I5: (tmdl) Trace the relationship graph for multiple active paths between any two AI-visible tables. [equals 1] | J5: Deactivate redundant relationships and expose the alternate path through an explicit measure using USERELATIONSHIP. | K5: Same question, different answer, depending on the path chosen. | L5: Copilot in Power BI tutorial: prepare a semantic model for AI | M5: documented | N5: unknown | T5: 5
A6: MOD-004 | B6: Role-playing relationships are marked inactive and surfaced through measures | C6: high | D6: modeling | E6: copilot-powerbi | F6: Role-playing dimension relationships must be marked inactive where appropriate, with active/inactive state clearly specified. | G6: Direct guidance to clearly specify active and inactive relationships and mark role-playing relationships inactive when appropriate. | I6: (dax) For dimensions related more than once to a fact, confirm exactly one active relationship and named measures for the inactive roles. [expected: one active, roles exposed via measures] | J6: Create measures such as Sales by Ship Date using USERELATIONSHIP, and name them so the role is obvious. | K6: Date-based questions silently resolve against the wrong date role. | L6: Optimize your semantic model for Copilot in Power BI | M6: documented | N6: unknown | T6: 5
A7: MOD-005 | B7: A marked date table with hierarchies exists | C7: critical | D7: modeling | E7: copilot-powerbi, fabric-data-agent | F7: The model must contain a dedicated date dimension with a logical drill hierarchy - Year > Quarter > Month > Day - and it must be marked as the date table. | G7: Hierarchies for drill-down are a stated structural requirement, and time intelligence in generated DAX depends on a proper date table. | I7: (dax) Confirm a date table exists, is marked as such, is contiguous, and exposes a Year/Quarter/Month/Day hierarchy. [expected: marked date table with hierarchy] | J7: Add and mark a conformed date dimension; remove auto date/time tables that clutter the AI-visible schema. | K7: Time-intelligence questions fail or return wrong periods - the most common category of user-facing Copilot error. | L7: Optimize your semantic model for Copilot in Power BI | M7: documented | N7: unknown | T7: 8
A8: MOD-006 | B8: Ambiguous date columns carry explicit default guidance | C8: high | D8: config | E8: copilot-powerbi, fabric-data-agent | F8: Where a model exposes several date columns - Order Date, Ship Date, Due Date - AI instructions or verified answers must state which is the default for each question type. | G8: Called out as a specific pitfall: multiple date columns require clear guidance or the AI is confused. Guidance is the fix, not removal. | I8: (manual) Count AI-visible date columns; if more than one, confirm AI instructions name the default and the conditions for using the others. [expected: documented default date guidance] | J8: Add an explicit line to AI instructions, for example: unless the user names a date type, use Order Date. | K8: Revenue questions answered on ship date; the numbers look plausible and are wrong. | L8: Semantic model best practices for data agent | M8: documented | N8: unknown | T8: 5
A9: MOD-007 | B9: Fact and dimension tables are explicitly named | C9: medium | D9: naming | E9: copilot-powerbi, fabric-data-agent | F9: Tables should be named so their role is unmistakable - FactSales, FactTransactions, DimProduct, DimCustomer - or follow an equivalent consistent convention. | G9: Explicit naming guidance. Role clarity in the name reduces the reasoning the generator must do before it can plan a query. | I9: (dax) Review AI-visible table names for a consistent, role-revealing convention. [expected: consistent convention] | J9: Adopt one convention and apply it uniformly. Consistency matters more than which convention you pick. | K9: The generator misclassifies a dimension as a fact and aggregates attributes. | L9: Optimize your semantic model for Copilot in Power BI | M9: documented | N9: unknown | T9: 3
A10: MOD-008 | B10: Unused tables, columns and measures are removed | C10: high | D10: modeling | E10: copilot-powerbi, fabric-data-agent | F10: Objects not required by any report or by the AI question scope must be removed from the model. | G10: Model bloat is named directly: remove unnecessary columns, tables and measures to reduce noise for the DAX generation tool. Every unused object is a candidate the generator must rule out. | I10: (vpax) Use the Semantic Model Memory Analyzer or a VPAX extract to identify unreferenced objects. [expected: no unreferenced AI-visible objects] | J10: Delete them, or at minimum hide and exclude them from the AI data schema. | K10: Higher token cost per question and more ways for the generator to go wrong. | L10: Semantic model best practices for data agent; Copilot in Power BI tutorial: prepare a semantic model for AI | M10: documented | N10: unknown | T10: 5
A11: MOD-009 | B11: Disconnected and field-parameter tables are limited | C11: high | D11: limit | E11: copilot-powerbi | F11: Disconnected tables, including field parameter tables, must be minimized in the AI-visible schema and documented where retained. | G11: Named as an unsupported complex pattern that may cause unexpected results, alongside currency conversion patterns. | I11: (tmdl) List AI-visible tables with no relationships; confirm each is deliberate and documented. [expected: minimized and documented] | J11: Exclude field parameter tables from the AI data schema; they are a report interactivity device, not a semantic concept. | K11: Unpredictable results on any question that touches the disconnected table. | L11: Use Copilot with semantic models in Power BI; Copilot in Power BI tutorial: prepare a semantic model for AI | M11: documented | N11: unknown | T11: 5
A12: MOD-010 | B12: Currency conversion patterns are flagged as unsupported | C12: medium | D12: limit | E12: copilot-powerbi | F12: Models implementing currency conversion must document that this pattern is not reliably supported and constrain the question scope accordingly. | G12: Currency conversion is explicitly listed among complex patterns that may cause unexpected results. | I12: (manual) Identify currency conversion logic and confirm the limitation is documented and tested. [expected: documented] | J12: Pre-compute reporting-currency measures and expose only those to the AI schema. | K12: Currency-denominated answers are wrong in ways that are hard to spot. | L12: Use Copilot with semantic models in Power BI | M12: documented | N12: unknown | T12: 3

Sheet Names, descriptions & linguisti
A1: Names, descriptions & linguistics - 10 rules, area weight 11 | J1: Fill the yellow cells only. Result must be one of: unknown, pass, partial, fail, na
A2: Rule ID | B2: Title | C2: Severity | D2: Type | E2: Applies to | F2: Requirement | G2: Why it matters | H2: Hard limit | I2: How to check | J2: Remediation | K2: If not fixed | L2: Source | M2: Basis | N2: Result | O2: Evidence / link | P2: Owner | Q2: Due date | R2: Notes | T2: _weight
A3: MET-001 | B3: Descriptions exist on every AI-visible table, column and measure | C3: critical | D3: metadata | E3: copilot-powerbi, fabric-data-agent | F3: Every table, column and measure in the AI data schema must carry a description. | G3: Adding descriptions to tables, columns and measures is a stated requirement so the model can understand purpose. Descriptions are the only place where business meaning reaches the generator. | I3: (dax) Compute description coverage across AI-visible objects via INFO functions or a TMDL scan. Report percentage complete. [gte 100 percent of AI-visible objects] | J3: Write descriptions for the AI-visible subset only - which is another reason to keep that subset small. | K3: The generator maps user language to fields on name similarity alone. | L3: Optimize your semantic model for Copilot in Power BI; Semantic model best practices for data agent | M3: documented | N3: unknown | T3: 8
A4: MET-002 | B4: The essential content of every description sits in the first 200 characters | C4: critical | D4: limit | E4: copilot-powerbi, fabric-data-agent | F4: Descriptions must front-load their meaning: only the first 200 characters are used by Copilot, and semantic model property descriptions are truncated at 200 characters. | G4: This is the single most commonly violated hard limit in Copilot preparation. Teams write thorough 600-character descriptions and two thirds of the content is discarded before the generator sees it. | H4: 200 characters (hard) | I4: (dax) For every AI-visible object, measure description length. Flag any description over 200 characters, and manually confirm the first 200 characters are self-sufficient. [lte 200 characters] | J4: Rewrite so the first sentence carries the definition and the usage note. Treat 200 characters as the whole budget, not a soft target. | K4: The disambiguating half of your documentation is silently discarded, and the model looks documented while behaving as if it is not. | L4: Optimize your semantic model for Copilot in Power BI; Use Copilot with semantic models in Power BI | M4: documented | N4: unknown | T4: 8
A5: MET-003 | B5: Descriptions state usage guidance, not just a restatement of the name | C5: high | D5: metadata | E5: copilot-powerbi, fabric-data-agent | F5: Descriptions must add information the name does not already carry - what the measure means, when to use it, what to pair it with, and any caveat. | G5: The documented model description pattern demonstrates this: it defines the calculation and then states which column to use it with. A description reading 'Total Sales measure' costs 200 characters of budget and adds nothing. | I5: (manual) Sample descriptions and score them for added information beyond the object name. [expected: informative descriptions] | J5: Follow the pattern: definition, then usage guidance. For example, year-over-year difference in orders, used with Date[Year] to show years other than the latest. | K5: Description coverage looks complete on a report while delivering no disambiguation. | L5: Optimize your semantic model for Copilot in Power BI | M5: documented | N5: unknown | T5: 5
A6: MET-004 | B6: Descriptions are prioritized where names are ambiguous | C6: high | D6: metadata | E6: copilot-powerbi, fabric-data-agent | F6: Descriptions must be present for abbreviated or generic object names, columns holding codes, flags, units or category values, date columns tied to a specific business event, and any object in a large schema. | G6: This is the documented priority list for where descriptions earn their keep. It gives you an order of work when full coverage is not yet achievable. | I6: (manual) Identify objects in each named category and confirm description coverage on them specifically. [gte 100 percent of priority objects] | J6: Work the priority list before chasing blanket coverage. | K6: Effort spread evenly while the genuinely ambiguous objects stay undocumented. | L6: Best practices for configuring your data agent | M6: documented | N6: unknown | T6: 5
A7: MET-005 | B7: Synonyms are populated in the linguistic schema | C7: high | D7: metadata | E7: copilot-powerbi | F7: Business synonyms and alternative phrasings must be registered in the model's linguistic schema for AI-visible objects. | G7: Field synonyms and the full model linguistic schema are supplied as grounding data. Synonyms are how the generator bridges the gap between how the business speaks and how the model is named. | I7: (tmdl) Inspect the linguistic schema for synonym coverage on AI-visible objects; flag objects with only the default term. [expected: synonyms on business-facing objects] | J7: Harvest synonyms from actual user questions and support tickets rather than inventing them. | K7: Users phrase questions in their own vocabulary and Copilot fails to map it. | L7: Use Copilot with semantic models in Power BI; Copilot in Power BI tutorial: prepare a semantic model for AI | M7: documented | N7: unknown | T7: 5
A8: MET-006 | B8: Q&A is enabled on the semantic model | C8: blocker | D8: enablement | E8: copilot-powerbi, fabric-data-agent | F8: Power BI Q&A must be enabled on every semantic model in scope for Prep for AI features and advanced DAX generation. | G8: Stated as a hard prerequisite: you must enable Q&A on your semantic model. Advanced DAX generation requires the Q&A setting, which is on by default for Import and Direct Lake models but must be verified. | I8: (api) Check the Q&A setting on every in-scope semantic model. [expected: enabled] | J8: Enable Q&A in semantic model settings. | K8: Prep for AI features and instance-value-aware DAX generation do not function. | L8: Prepare your data for AI to improve Copilot results (preview); Semantic model best practices for data agent | M8: documented | N8: unknown | T8: 13
A9: MET-007 | B9: Q&A retirement in December 2026 is tracked as a dependency | C9: medium | D9: governance | E9: copilot-powerbi, fabric-data-agent | F9: The roadmap must record that Q&A retires in December 2026 and that a replacement setting will carry instance value indexing forward, with an owner assigned to track the transition. | G9: Advanced DAX generation currently depends on the Q&A setting. A dated retirement of a dependency your AI surface relies on needs an owner before the date, not after. | H9: 2026-12 date (hard) | I9: (manual) Confirm the retirement is on the roadmap register with a named owner and review date. [expected: tracked] | J9: Add it to the platform dependency register and re-check the replacement setting each quarter. | K9: A dated platform change lands unmanaged on a production AI surface. | L9: Semantic model best practices for data agent | M9: documented | N9: unknown | T9: 3
A10: MET-008 | B10: Report visuals carry descriptive titles | C10: medium | D10: metadata | E10: copilot-powerbi | F10: Visuals on reports within the AI surface must have descriptive titles rather than default or decorative ones. | G10: Preparing report visuals with descriptive titles is a step in the documented implementation workflow, and report metadata from the current page is grounding data for questions about visuals. | I10: (manual) Sample in-scope report pages and review visual titles for descriptiveness. [expected: descriptive titles] | J10: Retitle visuals to name the metric and the grain, for example Revenue by Region, Last 12 Months. | K10: Weak grounding for visual-level questions and poorer report summaries. | L10: Semantic model best practices for data agent; Use Copilot with semantic models in Power BI | M10: documented | N10: unknown | T10: 3
A11: MET-009 | B11: Hierarchies are defined for natural drill paths | C11: medium | D11: modeling | E11: copilot-powerbi | F11: Logical hierarchies must be defined for drill-down on the main dimensions - date, geography, product and organization. | G11: Establishing logical groupings for drill-down is a stated structural requirement. | I11: (dax) List defined hierarchies and compare against the main AI-visible dimensions. [expected: hierarchies on principal dimensions] | J11: Define hierarchies and describe them so drill intent is unambiguous. | K11: Drill-oriented questions answered at the wrong grain. | L11: Optimize your semantic model for Copilot in Power BI | M11: documented | N11: unknown | T11: 3
A12: MET-010 | B12: Refresh timeliness is communicated in metadata | C12: medium | D12: metadata | E12: copilot-powerbi, fabric-data-agent | F12: The refresh schedule and data currency must be stated in the semantic model description or AI instructions. | G12: Clearly communicating data timeliness through refresh schedules is a stated metadata requirement. Without it, an answer carries no indication of how current it is. | I12: (manual) Confirm data currency is stated in the model description or AI instructions. [expected: stated] | J12: Add a line such as: data refreshes nightly at 02:00 UTC; today's transactions are not included. | K12: Decisions made on stale figures presented without qualification. | L12: Optimize your semantic model for Copilot in Power BI | M12: documented | N12: unknown | T12: 3

Sheet Measures & DAX
A1: Measures & DAX - 12 rules, area weight 9 | J1: Fill the yellow cells only. Result must be one of: unknown, pass, partial, fail, na
A2: Rule ID | B2: Title | C2: Severity | D2: Type | E2: Applies to | F2: Requirement | G2: Why it matters | H2: Hard limit | I2: How to check | J2: Remediation | K2: If not fixed | L2: Source | M2: Basis | N2: Result | O2: Evidence / link | P2: Owner | Q2: Due date | R2: Notes | T2: _weight
A3: MEA-001 | B3: Explicit measures exist for every metric users will ask about | C3: critical | D3: modeling | E3: copilot-powerbi, fabric-data-agent | F3: Every business metric within the question scope must be implemented as an explicit DAX measure. | G3: Explicit measures are required; implicit measures lead to unpredictable results. If the metric is not a measure, the generator has to invent the aggregation. | I3: (dax) Map each metric in the question scope to a named measure. Flag any metric with no measure. [expected: measure per in-scope metric] | J3: Create the measures, name them the way the business names them, and describe them. | K3: Invented aggregations that do not match the organization's official definition. | L3: Semantic model best practices for data agent; Optimize your semantic model for Copilot in Power BI | M3: documented | N3: unknown | T3: 8
A4: MEA-002 | B4: Implicit measures are suppressed on AI-visible numeric columns | C4: high | D4: modeling | E4: copilot-powerbi, fabric-data-agent | F4: Numeric columns in the AI schema must not rely on implicit aggregation where an explicit measure is the intended answer. | G4: Implicit measures are named as a pitfall producing unpredictable results. A raw numeric column adjacent to a proper measure gives the generator a wrong-but-available option. | I4: (dax) For AI-visible numeric columns, confirm either an explicit measure covers the metric and the raw column is excluded, or the column's default summarization is deliberately set. [expected: no unintended implicit aggregation] | J4: Exclude raw fact numeric columns from the AI schema once explicit measures exist. | K4: SUM of a raw column returned where a ratio or filtered measure was correct. | L4: Semantic model best practices for data agent | M4: documented | N4: unknown | T4: 5
A5: MEA-003 | B5: Default summarization is set correctly on numeric columns | C5: high | D5: modeling | E5: copilot-powerbi | F5: Every AI-visible numeric column must have a deliberate default summarization - Sum, Average or None - rather than the inherited default. | G5: Stated requirement, to prevent unintended aggregations. Averaging a ratio column or summing a year is the classic failure. | I5: (dax) Read the summarizeBy property for AI-visible numeric columns. Flag ratio, percentage, year and key columns not set to None. [expected: deliberate summarizeBy on every numeric column] | J5: Set summarizeBy to None on identifiers, years and ratios; set Sum or Average deliberately elsewhere. | K5: Summed percentages and averaged keys presented as fact. | L5: Semantic model best practices for data agent | M5: documented | N5: unknown | T5: 5
A6: MEA-004 | B6: Helper and intermediate measures are excluded from the AI schema | C6: high | D6: modeling | E6: copilot-powerbi, fabric-data-agent | F6: Only measures that calculate an actual business metric may be AI-visible; helper measures and intermediate objects used for report interactivity must be excluded. | G6: Direct instruction. Including unnecessary measures increases noise and decreases accuracy. | I6: (manual) Classify every AI-visible measure as business metric or helper; flag helpers. [expected: business metrics only] | J6: Hide helper measures and exclude them from the AI data schema; keep them in a clearly named technical display folder. | K6: Answers built on formatting or selection-state helpers that were never meant to be reported. | L6: Semantic model best practices for data agent | M6: documented | N6: unknown | T6: 5
A7: MEA-005 | B7: Near-duplicate measures are eliminated or clearly differentiated | C7: critical | D7: modeling | E7: copilot-powerbi, fabric-data-agent | F7: The AI schema must not expose several measures meaning approximately the same thing - Total Sales, Sales Amount, Revenue - unless each carries a description that makes the distinction explicit. | G7: Named as a pitfall creating ambiguity for DAX generation. This is one of the most common causes of two users getting two different numbers for the same question. | I7: (dax) Cluster AI-visible measure names by semantic similarity; review each cluster for genuine distinction. [equals 0] | J7: Keep one canonical measure per concept. Where variants are genuinely needed, encode the distinction in the name and describe it. | K7: Inconsistent answers to the same business question, which is the fastest route to losing executive trust. | L7: Semantic model best practices for data agent | M7: documented | N7: unknown | T7: 8
A8: MEA-006 | B8: Measures are named in business language, not technical shorthand | C8: critical | D8: naming | E8: copilot-powerbi, fabric-data-agent | F8: Measure and column names must be descriptive business terms - Average Customer Rating rather than AvgRating, Total Revenue rather than TR_AMT, Sales Region rather than DIM_GEO_01. | G8: Stated with these exact examples. Abbreviations and acronyms increase error probability, and non-descriptive naming leaves the DAX tool with no context at all. | I8: (dax) Scan AI-visible object names for abbreviations, underscores, all-caps tokens and source-system prefixes. [expected: business-friendly names throughout] | J8: Rename in the semantic layer. Source-system names belong in Power Query, not in the AI-visible model. | K8: The generator has no basis for mapping a user's words to your fields. | L8: Semantic model best practices for data agent; Optimize your semantic model for Copilot in Power BI; Use Copilot with semantic models in Power BI | M8: documented | N8: unknown | T8: 8
A9: MEA-007 | B9: Commonly requested measures are pre-built rather than left to generation | C9: high | D9: modeling | E9: copilot-powerbi, fabric-data-agent | F9: Frequently requested calculations - YTD, month-over-month growth, prior-year comparison, run rate - must exist as measures instead of relying on the generator to compose them. | G9: Guidance to include commonly requested measures users are likely to need, with YTD Sales and MoM Growth given as examples. Pre-built beats generated every time on both accuracy and cost. | I9: (manual) Compare the top question patterns against the measure inventory; flag common patterns with no backing measure. [expected: measures for common patterns] | J9: Build the top time-intelligence and comparison measures explicitly. Each one removes a whole class of generation errors. | K9: The generator writes time intelligence from scratch on every question, slowly and sometimes wrongly. | L9: Optimize your semantic model for Copilot in Power BI | M9: documented | N9: unknown | T9: 5
A10: MEA-008 | B10: Business KPIs are defined in the model | C10: medium | D10: modeling | E10: copilot-powerbi | F10: Business-relevant KPIs such as ROI, CAC and LTV should be defined as measures where they are part of the question scope. | G10: Stated as a requirement with these examples. A KPI the business talks about but the model does not contain is a guaranteed hallucination opportunity. | I10: (manual) Compare the business KPI catalogue to the measure inventory. [expected: KPI measures present] | J10: Implement the KPIs with the official definitions and describe the calculation basis. | K10: Users ask for a named KPI and receive an approximation the generator assembled. | L10: Optimize your semantic model for Copilot in Power BI | M10: documented | N10: unknown | T10: 3
A11: MEA-009 | B11: Calculation groups carry item names in the description | C11: high | D11: metadata | E11: copilot-powerbi | F11: Every calculation group must have a description that lists and explains its calculation items, within the first 200 characters. | G11: Copilot struggles to use calculation groups; the documented mitigation is to include the calculation item names in the description, which is truncated at 200 characters. | H11: 200 characters (hard) | I11: (dax) For each calculation group, confirm the description names the items and that the essential content sits in the first 200 characters. [expected: item names within first 200 chars] | J11: Front-load the item names, then any explanation. Anything past character 200 is not read. | K11: Calculation groups are effectively invisible and time-intelligence answers ignore them. | L11: Optimize your semantic model for Copilot in Power BI; Use Copilot with semantic models in Power BI | M11: documented | N11: unknown | T11: 5
A12: MEA-010 | B12: DAX comments are not used to convey meaning to Copilot | C12: medium | D12: metadata | E12: copilot-powerbi | F12: Semantic context must live in descriptions, not in DAX comments. | G12: Comments in DAX expressions are explicitly excluded from grounding data. Teams document measures in comments and assume Copilot reads them. | I12: (dax) Sample measures with substantial comment blocks and confirm the same context exists in the description. [expected: context duplicated into description] | J12: Move the business meaning into the description; keep comments for maintainers. | K12: Carefully documented measures that Copilot understands no better than undocumented ones. | L12: Use Copilot with semantic models in Power BI | M12: documented | N12: unknown | T12: 3
A13: MEA-011 | B13: Newer DAX functions are used cautiously in AI-facing models | C13: low | D13: validation | E13: copilot-powerbi | F13: Where a model relies on recently introduced DAX functions or syntax, the team must test AI behaviour against those measures specifically. | G13: Copilot has limited training data for newer DAX functions and syntax and may produce mistakes with them. | I13: (manual) Identify measures using recent DAX functions and include them in the golden question set. [expected: covered by tests] | J13: Wrap the newer logic in a stable named measure so the generator references rather than rewrites it. | K13: Generation errors concentrated in the newest parts of the model. | L13: Use Copilot with semantic models in Power BI | M13: documented | N13: unknown | T13: 1
A14: MEA-012 | B14: Variable-heavy measures are validated for filter and grouping behaviour | C14: medium | D14: validation | E14: copilot-powerbi | F14: Measures making heavy use of DAX variables must be tested, because Copilot may inappropriately filter or group on already-declared variables. | G14: Named as a specific known failure mode. | I14: (manual) Include variable-heavy measures in the golden question set and inspect the generated DAX. [expected: tested] | J14: Simplify the public-facing measure and push variable complexity into helper measures excluded from the AI schema. | K14: Subtly wrong filter context in generated queries. | L14: Use Copilot with semantic models in Power BI | M14: documented | N14: unknown | T14: 3

Sheet Data types & data quality
A1: Data types & data quality - 5 rules, area weight 5 | J1: Fill the yellow cells only. Result must be one of: unknown, pass, partial, fail, na
A2: Rule ID | B2: Title | C2: Severity | D2: Type | E2: Applies to | F2: Requirement | G2: Why it matters | H2: Hard limit | I2: How to check | J2: Remediation | K2: If not fixed | L2: Source | M2: Basis | N2: Result | O2: Evidence / link | P2: Owner | Q2: Due date | R2: Notes | T2: _weight
A3: DAT-001 | B3: Data types are correct and consistent across tables | C3: critical | D3: modeling | E3: copilot-powerbi, fabric-data-agent | F3: Every AI-visible column must carry the correct data type - amounts as decimal, dates as date, identifiers as whole number - consistently across tables. | G3: Stated requirement with these exact examples. A numeric amount stored as text cannot be aggregated and the generator will not tell you why the answer is empty. | I3: (dax) Run the Best Practice Analyzer data type rules across AI-visible columns. [expected: correct types throughout] | J3: Fix types in Power Query or the source; do not paper over with DAX conversion in measures. | K3: Empty or wrong aggregations that look like missing data. | L3: Optimize your semantic model for Copilot in Power BI; Semantic model best practices for data agent | M3: documented | N3: unknown | T3: 8
A4: DAT-002 | B4: Categorical values are standardized | C4: high | D4: modeling | E4: copilot-powerbi, fabric-data-agent | F4: Values in AI-visible categorical columns must be standardized - Open, Closed, Pending - without mixed case, trailing whitespace, or synonym variants of the same state. | G4: Data consistency with standardized values is a stated requirement. Instance-value matching is literal; 'open', 'Open ' and 'OPEN' are three different filter targets. | I4: (dax) Profile distinct values per AI-visible categorical column; flag case and whitespace variants of the same value. [expected: standardized values] | J4: Normalize in the transformation layer and add a data quality test to keep it normalized. | K4: Filters match a subset of the rows they should, producing understated numbers that look valid. | L4: Optimize your semantic model for Copilot in Power BI | M4: documented | N4: unknown | T4: 5
A5: DAT-003 | B5: Format strings are set on AI-visible measures and columns | C5: medium | D5: metadata | E5: copilot-powerbi | F5: Measures and columns must carry appropriate format strings, since format string is part of the grounding data. | G5: Format strings are listed among the semantic model properties supplied as grounding data in both the data-question and DAX query view paths. They tell the generator whether a number is currency, a percentage or a count. | I5: (dax) List AI-visible measures and numeric columns with empty or default format strings. [expected: explicit format strings] | J5: Set currency, percentage and precision formats explicitly. | K5: Percentages presented as raw decimals and currency without denomination. | L5: Use Copilot with semantic models in Power BI | M5: documented | N5: unknown | T5: 3
A6: DAT-004 | B6: Data categories are set where they carry semantic meaning | C6: low | D6: metadata | E6: copilot-powerbi | F6: Columns representing geography, URLs, images or barcodes must have the appropriate data category set. | G6: Data category is explicitly part of the grounding data supplied to Copilot. | I6: (dax) Check data category on geographic and URL columns in the AI schema. [expected: set where applicable] | J6: Set City, State/Province, Country and Postal Code categories on the relevant columns. | K6: Weaker map visual selection and geographic reasoning. | L6: Use Copilot with semantic models in Power BI | M6: documented | N6: unknown | T6: 1
A7: DAT-005 | B7: High-cardinality columns are identified and justified | C7: high | D7: performance | E7: copilot-powerbi, fabric-data-agent | F7: High-cardinality columns must be identified with the Semantic Model Memory Analyzer and either removed, or justified and excluded from the AI data schema. | G7: Named as a target of analysis alongside incorrect data types and inefficient DAX. High cardinality drives both model size and the instance-value index budget. | I7: (vpax) Rank AI-visible columns by cardinality from a VPAX extract; review the top of the list for necessity. [expected: reviewed and justified] | J7: Remove, bucket, or exclude from the AI schema. A transaction ID needs no place in a natural-language surface. | K7: Index budget exhausted by columns nobody asks about, starving the ones they do. | L7: Semantic model best practices for data agent | M7: documented | N7: unknown | T7: 5

Sheet Security, RLS & compliance
A1: Security, RLS & compliance - 8 rules, area weight 8 | J1: Fill the yellow cells only. Result must be one of: unknown, pass, partial, fail, na
A2: Rule ID | B2: Title | C2: Severity | D2: Type | E2: Applies to | F2: Requirement | G2: Why it matters | H2: Hard limit | I2: How to check | J2: Remediation | K2: If not fixed | L2: Source | M2: Basis | N2: Result | O2: Evidence / link | P2: Owner | Q2: Due date | R2: Notes | T2: _weight
A3: SEC-001 | B3: RLS is defined for sensitive data reachable by AI | C3: blocker | D3: security | E3: copilot-powerbi, fabric-data-agent | F3: Row-level security roles must be defined and assigned for any sensitive data reachable through a Copilot or agent surface. | G3: Defining role-level access for sensitive data is a stated metadata and security requirement. AI surfaces do not create new security, but they do remove the friction that used to limit exposure. | I3: (dax) Enumerate RLS roles and their assignments for in-scope models; confirm coverage of the sensitive tables identified in the data classification. [expected: RLS defined and assigned] | J3: Define the roles, assign the groups, and test with View As before enabling AI on the model. | K3: Conversational access to data the user was never intended to see. | L3: Optimize your semantic model for Copilot in Power BI | M3: documented | N3: unknown | T3: 13
A4: SEC-002 | B4: RLS behaviour is tested through the AI surface itself, not only in reports | C4: critical | D4: security | E4: copilot-powerbi, fabric-data-agent | F4: Every RLS role must be tested by asking representative questions through Copilot and through each data agent, not only by validating reports. | G4: Report-level RLS validation does not exercise the generated-query path. The generator composes queries no report author wrote, and those are the queries whose security behaviour matters here. | I4: (manual) For each role, run the golden question set as a member of that role and confirm results are correctly restricted. [expected: per-role AI test evidence] | J4: Add per-role AI testing to the release checklist with recorded evidence. | K4: An RLS gap that only manifests on generated queries reaches production undetected. | L4: Established semantic modeling / Copilot tuning practice (not a single Microsoft doc); Optimize your semantic model for Copilot in Power BI | M4: inferred | N4: unknown | T4: 8
A5: SEC-003 | B5: Report metadata sensitivity is assessed before enabling Copilot | C5: critical | D5: security | E5: copilot-powerbi | F5: Before enabling Copilot on a report, confirm that report metadata - which can include column values - does not carry data unsuitable for transmission to the AI service. | G5: Explicit caution: report metadata may contain sensitive data such as column values, and it forms part of the grounding data sent for questions about visuals. | I5: (manual) Review in-scope reports for hard-coded filter values, slicer defaults and titles containing sensitive identifiers. [expected: assessment recorded] | J5: Remove sensitive literals from report metadata, or exclude the report from the AI surface. | K5: Sensitive values leave the tenant boundary inside grounding data. | L5: Use Copilot with semantic models in Power BI | M5: documented | N5: unknown | T5: 8
A6: SEC-004 | B6: Agent permission model is understood - read access, not Build | C6: high | D6: security | E6: fabric-data-agent | F6: The agent access design must reflect that a Power BI semantic model source requires only Read permission, not Build, and that the agent operates with the consuming user's read access. | G6: Stated directly. Teams often assume Build permission gates agent access and design their security around an assumption that does not hold. | I6: (manual) Document the permission required per source type and confirm the access design matches. [expected: documented and matching] | J6: Re-derive the access design from actual permission requirements and re-test with a least-privileged account. | K6: Broader effective access than the security design intended. | L6: Fabric data agent creation | M6: documented | N6: unknown | T6: 5
A7: SEC-005 | B7: Agents are confirmed read-only against every source | C7: medium | D7: security | E7: fabric-data-agent | F7: Confirm and document that agents issue only read queries - no create, update or delete - across SQL, DAX and KQL sources. | G7: Documented behaviour, and worth recording explicitly because it is the question every security reviewer asks first. | I7: (manual) Record the read-only constraint in the security design and confirm source permissions do not grant write regardless. [expected: documented and enforced at source] | J7: Grant the agent's effective identity read-only permissions at the source as defence in depth. | K7: Reliance on application behaviour where a source permission would be the durable control. | L7: Fabric data agent creation | M7: documented | N7: unknown | T7: 3
A8: SEC-006 | B8: Non-Fabric consumption paths are assessed for compliance boundary exit | C8: critical | D8: security | E8: fabric-data-agent | F8: Where agents are consumed from Microsoft Foundry, Copilot Studio, Microsoft 365 Copilot or an MCP server, the compliance implication must be assessed and approved. | G8: Explicit warning: responses consumed from non-Fabric services may be sent outside Fabric's compliance boundary or geographic region, governed by the consuming service's terms rather than Fabric's. | I8: (manual) List every consumption surface per agent and confirm compliance sign-off for each non-Fabric path. [expected: sign-off per external surface] | J8: Restrict external consumption to agents whose data classification permits it. | K8: Regulated data leaves the assessed compliance boundary through a surface nobody reviewed. | L8: Configure Fabric data agent tenant settings | M8: documented | N8: unknown | T8: 8
A9: SEC-007 | B9: Sensitivity labels are applied and their AI behaviour understood | C9: medium | D9: security | E9: copilot-powerbi, fabric-data-agent | F9: In-scope semantic models and reports must carry sensitivity labels consistent with the organization's classification scheme. | G9: Labels are the mechanism through which downstream protection and DLP decisions are made on AI-surfaced content. | I9: (api) Report label coverage across in-scope items. [gte 100 percent of in-scope items] | J9: Apply labels and enforce mandatory labelling on AI-enabled workspaces. | K9: No basis for downstream protection decisions on AI output. | L9: Established semantic modeling / Copilot tuning practice (not a single Microsoft doc); Fabric data agent creation | M9: inferred | N9: unknown | T9: 3
A10: SEC-008 | B10: Object-level security interaction with AI grounding is tested | C10: medium | D10: security | E10: copilot-powerbi | F10: Where OLS is in use, confirm through testing how restricted objects behave in Copilot grounding and in generated queries. | G10: OLS restricts metadata visibility, which interacts with schema grounding in ways that need empirical confirmation on your own model rather than assumption. | I10: (manual) Test as an OLS-restricted user and record whether restricted objects appear in grounding or generated DAX. [expected: tested and recorded] | J10: Record actual observed behaviour per model and feed it into the security design. | K10: OLS assumptions that do not hold on the AI path. | L10: Established semantic modeling / Copilot tuning practice (not a single Microsoft doc) | M10: inferred | N10: unknown | T10: 3

Sheet Verified answers
A1: Verified answers - 7 rules, area weight 6 | J1: Fill the yellow cells only. Result must be one of: unknown, pass, partial, fail, na
A2: Rule ID | B2: Title | C2: Severity | D2: Type | E2: Applies to | F2: Requirement | G2: Why it matters | H2: Hard limit | I2: How to check | J2: Remediation | K2: If not fixed | L2: Source | M2: Basis | N2: Result | O2: Evidence / link | P2: Owner | Q2: Due date | R2: Notes | T2: _weight
A3: VER-001 | B3: Verified answers exist for the highest-frequency questions | C3: critical | D3: config | E3: copilot-powerbi, fabric-data-agent | F3: The most frequently asked and highest-consequence questions in the scope must be covered by verified answers rather than left to generation. | G3: A verified answer returns a curated visual instead of triggering DAX generation. It is the most direct fix for both latency and correctness on the questions that matter most, and it is the mechanism that stops repeated broad scans for the same recurring question. | I3: (manual) Rank in-scope questions by frequency and consequence; confirm the top tier has verified answers. [expected: coverage of top-tier questions] | J3: Build verified answers from existing report visuals for the top questions before tuning anything else. | K3: Every recurring question re-plans a query from scratch, at full token and scan cost, with non-deterministic results. | L3: Semantic model best practices for data agent; Copilot in Power BI tutorial: prepare a semantic model for AI | M3: documented | N3: unknown | T3: 8
A4: VER-002 | B4: Each verified answer carries five to seven trigger questions | C4: high | D4: config | E4: copilot-powerbi | F4: Every verified answer should define roughly five to seven trigger questions covering natural variations in phrasing, including both formal and conversational wording. | G4: Stated explicitly as five to seven trigger questions per verified answer. Too few and the answer never fires; the trigger set is what determines hit rate. | H4: 5-7 trigger questions per verified answer (soft) | I4: (manual) Count trigger questions per verified answer and review phrasing variety. [between [5, 7] trigger questions] | J4: Harvest real phrasings from usage logs and support requests rather than writing variations from imagination. | K4: Verified answers exist but rarely fire, so the tuning effort produces no measurable benefit. | L4: Semantic model best practices for data agent | M4: documented | N4: unknown | T4: 5
A5: VER-003 | B5: Verified answers use no more than three filters | C5: medium | D5: limit | E5: copilot-powerbi | F5: Configure up to three filters per verified answer to keep it flexible for slicing. | G5: Documented limit of three filters per verified answer. | H5: 3 filters per verified answer (hard) | I5: (manual) Count configured filters per verified answer. [lte 3 filters] | J5: Where more slicing is needed, create a second verified answer rather than overloading one. | K5: Configuration rejected or the answer becomes too narrow to fire. | L5: Semantic model best practices for data agent | M5: documented | N5: unknown | T5: 3
A6: VER-004 | B6: No verified answer references a hidden column | C6: critical | D6: config | E6: copilot-powerbi | F6: Verified answers must not reference hidden columns or measures. | G6: Stated flatly: verified answers will not work if they reference hidden columns. The failure is silent, which makes it expensive to diagnose. | I6: (manual) For each verified answer, resolve referenced objects and confirm none are hidden. [equals 0] | J6: Unhide the referenced object or rebuild the verified answer on a visible equivalent. | K6: Verified answers silently never fire and the team concludes the feature does not work. | L6: Semantic model best practices for data agent | M6: documented | N6: unknown | T6: 8
A7: VER-005 | B7: Verified answers are re-saved after any referenced object is renamed | C7: high | D7: operations | E7: copilot-powerbi | F7: Renaming a table, column or measure referenced by a verified answer requires updating and re-saving that verified answer. | G7: Explicit rule. Renames are routine during model tuning, so this breaks constantly unless it is part of the change process. | I7: (manual) Confirm the model change process includes a verified-answer revalidation step after renames. [expected: step present in change process] | J7: Add verified answer revalidation to the rename checklist and to the release pipeline. | K7: A cosmetic rename silently disables the curated answers protecting your top questions. | L7: Semantic model best practices for data agent | M7: documented | N7: unknown | T7: 5
A8: VER-006 | B8: Verified answer authoring prerequisites are met | C8: medium | D8: enablement | E8: copilot-powerbi | F8: Authors creating verified answers in the Power BI service must be in a Copilot-enabled workspace, hold authoring permission on the underlying semantic model, be on a report page in edit mode, with the visual selected. | G8: All five conditions are documented prerequisites. When the option is greyed out, one of them is unmet - this list is the diagnostic. | I8: (manual) Confirm the authoring team meets all five conditions and that the checklist is in the authoring guide. [expected: all prerequisites met] | J8: Publish the five conditions in the authoring guide as a troubleshooting checklist. | K8: Authors blocked with no visible reason and the capability goes unused. | L8: Prepare your data for AI to improve Copilot results (preview) | M8: documented | N8: unknown | T8: 3
A9: VER-007 | B9: Verified answer coverage is measured against actual question volume | C9: high | D9: validation | E9: copilot-powerbi | F9: The proportion of real user questions answered by a verified answer rather than by generation must be measured and tracked over time. | G9: Coverage is the leading indicator for both cost and consistency. It is also the only way to know whether verified-answer investment is paying back. | I9: (manual) Sample real questions over a period and classify each as verified-answer hit or generated. Report the hit rate. [gte 40 percent of questions (recommended starting target)] | J9: Feed the miss list back into verified answer creation each cycle. The threshold here is a working target, not a Microsoft-published figure. | K9: No feedback loop; verified answers stay frozen at their initial guess of what users would ask. | L9: Established semantic modeling / Copilot tuning practice (not a single Microsoft doc) | M9: inferred | N9: unknown | T9: 5

Sheet AI instructions
A1: AI instructions - 5 rules, area weight 6 | J1: Fill the yellow cells only. Result must be one of: unknown, pass, partial, fail, na
A2: Rule ID | B2: Title | C2: Severity | D2: Type | E2: Applies to | F2: Requirement | G2: Why it matters | H2: Hard limit | I2: How to check | J2: Remediation | K2: If not fixed | L2: Source | M2: Basis | N2: Result | O2: Evidence / link | P2: Owner | Q2: Due date | R2: Notes | T2: _weight
A3: INS-001 | B3: AI instructions exist and carry business context | C3: critical | D3: config | E3: copilot-powerbi | F3: AI instructions must be configured with industry and business context, key terminology definitions, table and field mapping guidance, measure specifications and synonyms, and audience prioritization rules. | G3: These five content elements are the documented structure. AI instructions influence more Copilot capabilities than any other single configuration - report summary, questions about visuals, questions about the semantic model, create report page, and DAX query. | I3: (manual) Review the AI instructions against the five required content elements. [expected: all five elements present] | J3: Structure the instructions on the documented template, then test with real questions. | K3: The generator has no map from business vocabulary to model objects. | L3: Copilot in Power BI tutorial: prepare a semantic model for AI; Frequently asked questions about preparing data for AI | M3: documented | N3: unknown | T3: 8
A4: INS-002 | B4: AI instructions are configured in Prep for AI, not at data agent level, for semantic models | C4: critical | D4: config | E4: fabric-data-agent | F4: For semantic model sources, AI instructions must be set in Prep for AI. Data agent level instructions are ignored for semantic model DAX generation. | G4: Stated as a direct rule. This is a high-frequency configuration mistake: teams write careful agent instructions for a semantic model source and none of it reaches the DAX generator. | I4: (manual) For each semantic model source, confirm the substantive instructions live in Prep for AI and that agent-level instructions contain only cross-source guidance. [expected: instructions in Prep for AI] | J4: Move semantic model guidance into Prep for AI; keep agent instructions for formatting, routing, abbreviations and tone across sources. | K4: Instructions written, paid for in tokens, and ignored by the generator. | L4: Semantic model best practices for data agent | M4: documented | N4: unknown | T4: 8
A5: INS-003 | B5: Instructions are focused and specific rather than long and complex | C5: high | D5: config | E5: copilot-powerbi, fabric-data-agent | F5: AI instructions must be kept focused and specific; conflicting or overly complex instructions must be avoided. | G5: Documented on two counts: clear instructions are more effective than complex or conflicting ones, and overly complex instructions reduce accuracy while increasing latency. Instructions are also billed as input tokens on every single request, so verbosity has a direct and recurring CU cost. | I5: (manual) Review instruction length and internal consistency; flag contradictory directives and unbounded lists. [expected: focused, non-contradictory instructions] | J5: Cut instructions to the rules that changed behaviour in testing. Measure the token cost per request before and after. | K5: Higher latency, higher CU burn on every question, and lower accuracy. | L5: Semantic model best practices for data agent; Data agent consumption | M5: documented | N5: unknown | T5: 5
A6: INS-004 | B6: Instructions map user terminology to model objects | C6: high | D6: config | E6: copilot-powerbi, fabric-data-agent | F6: Instructions must explicitly map the terms users say to the tables, measures and columns they mean, including synonyms and abbreviations. | G6: The documented example does exactly this: routing Clients, Customers and Organizations to the Accounts table, and Leads, Deals and Sales Prospects to the opportunities table. Terminology mapping is the highest-yield content in an instruction set. | I6: (manual) Confirm the instructions contain explicit term-to-object mappings covering the main business vocabulary. [expected: terminology mappings present] | J6: Build the mapping from observed user language, not from the data dictionary. | K6: Correct questions in the users' own words routed to the wrong table. | L6: Copilot in Power BI tutorial: prepare a semantic model for AI | M6: documented | N6: unknown | T6: 5
A7: INS-005 | B7: Instructions are treated as influence, not guarantee | C7: medium | D7: governance | E7: copilot-powerbi, fabric-data-agent | F7: Governance documentation and user communication must state that the model interprets instructions but does not guarantee following them exactly. | G7: Stated directly. It sets the expectation that instructions reduce error rates rather than eliminate them, which is essential framing for any validity discussion. | I7: (manual) Confirm the limitation is stated in the governance documentation and user-facing guidance. [expected: documented] | J7: State it plainly and pair every critical instruction with a verified answer where correctness genuinely matters. | K7: Instructions treated as a control they are not, leaving critical answers unprotected. | L7: Semantic model best practices for data agent | M7: documented | N7: unknown | T7: 3

Sheet Fabric data agent configuration
A1: Fabric data agent configuration - 10 rules, area weight 10 | J1: Fill the yellow cells only. Result must be one of: unknown, pass, partial, fail, na
A2: Rule ID | B2: Title | C2: Severity | D2: Type | E2: Applies to | F2: Requirement | G2: Why it matters | H2: Hard limit | I2: How to check | J2: Remediation | K2: If not fixed | L2: Source | M2: Basis | N2: Result | O2: Evidence / link | P2: Owner | Q2: Due date | R2: Notes | T2: _weight
A3: AGT-001 | B3: Data source instructions cover authoritative tables, joins, grain and default filters | C3: critical | D3: config | E3: fabric-data-agent | F3: Each data source's instructions must state the authoritative tables per subject, the join keys and required join paths, the table grain and deduplication rules, the default filters such as current or active records only, date logic including fiscal calendars and time-zone assumptions, and any required calculations or output columns. | G3: This is the documented content list for data source instructions, and it is the most direct available control on generated query shape. Default filters in particular are what stops a query scanning full history when the user meant current records. | I3: (manual) Review each source's instructions against the six documented content areas. [expected: all six areas covered] | J3: Write the instructions from the documented list, and be specific about default filters and grain. | K3: The agent scans wide, joins wrong, double-counts on grain, and returns history when the user meant now. | L3: Best practices for configuring your data agent | M3: documented | N3: unknown | T3: 8
A4: AGT-002 | B4: Example queries stay within 100 per data source and demonstrate reusable patterns | C4: high | D4: limit | E4: fabric-data-agent | F4: Each data source may carry up to 100 example queries. Each should demonstrate one reusable pattern - multi-table joins or required preaggregation, business-specific calculations, relative dates and fiscal periods or snapshot logic, filters mapping user terminology to stored values, and ranking or window functions. | G4: 100 per data source is the documented cap, and the pattern list is the documented prioritization. Examples are few-shot grounding: they are the most efficient way to teach correct query shape. | H4: 100 example queries per data source (hard) | I4: (manual) Count example queries per source and review each for a single clear reusable pattern. [lte 100 example queries per data source] | J4: Prioritize the five documented pattern categories. Keep each example focused on one pattern; fewer sharp examples beat many overlapping ones, and every example is billed as input tokens on each request. | K4: Query shapes are reinvented per question, inefficiently and inconsistently. | L4: Best practices for configuring your data agent; Fabric data agent creation; Data agent consumption | M4: documented | N4: unknown | T4: 5
A5: AGT-003 | B5: The 25 row by 25 column response cap is designed for, not discovered | C5: high | D5: limit | E5: fabric-data-agent | F5: Agent question scope and instructions must account for the maximum of 25 rows and 25 columns per response. | G5: Hard documented cap. An agent asked to list all customers will silently return a truncated view, and the user will not know it is truncated unless the design anticipated this. | H5: rows=25; columns=25 per response (hard) | I5: (manual) Review the question scope for enumeration-style questions and confirm instructions direct the agent to aggregate or rank rather than list. [lte {'rows': 25, 'columns': 25}] | J5: Instruct the agent to aggregate, rank or top-N by default, and to state when results are truncated. | K5: Silently truncated answers presented as complete. | L5: Fabric data agent creation | M5: documented | N5: unknown | T5: 5
A6: AGT-004 | B6: Agent instructions are reserved for cross-source concerns | C6: high | D6: config | E6: fabric-data-agent | F6: Agent-level instructions must cover only cross-source guidance - formatting, source routing, abbreviations and tone - with source-specific logic held at the source or in Prep for AI. | G6: Documented scope for agent-level instructions. Mixing source-specific logic into agent instructions both fails to reach the semantic model generator and inflates the token cost of every request across all sources. | I6: (manual) Review agent instructions for source-specific logic that belongs at source level. [expected: cross-source content only] | J6: Relocate source-specific content and keep the agent layer thin. | K6: Instructions that are simultaneously ignored where needed and billed everywhere. | L6: Semantic model best practices for data agent; Best practices for configuring your data agent | M6: documented | N6: unknown | T6: 5
A7: AGT-005 | B7: Time filters are required for KQL and time-series sources | C7: high | D7: performance | E7: fabric-data-agent | F7: For KQL and Eventhouse sources, agent instructions must direct the inclusion of time filters, and users must be guided to include a time range in their questions. | G7: Documented performance guidance for KQL time-series data. An unbounded time-series query is the purest form of the scan-everything behaviour. | I7: (manual) Confirm KQL source instructions mandate a default time window, and that the default is stated. [expected: default time window defined] | J7: Set an explicit default such as the last 7 days unless the user states otherwise, and have the agent state the window it used. | K7: Full-retention scans on every time-series question, at severe latency and CU cost. | L7: Fabric data agent creation; Best practices for configuring your data agent | M7: documented | N7: unknown | T7: 5
A8: AGT-006 | B8: Agent language scope is limited to English | C8: medium | D8: limit | E8: fabric-data-agent | F8: The rollout plan must record that non-English languages are not supported by Fabric data agents. | G8: Documented limitation. It determines which regions and business units can be in scope at all. | I8: (manual) Confirm the rollout scope and user communication state the English-only constraint. [expected: documented] | J8: Scope the audience accordingly and state it in the user guidance rather than letting users discover it. | K8: Non-English users receive poor answers and attribute it to model quality. | L8: Fabric data agent creation | M8: documented | N8: unknown | T8: 3
A9: AGT-007 | B9: Conversation history volatility is accounted for in user guidance | C9: medium | D9: governance | E9: fabric-data-agent | F9: User guidance must state that conversation history may not persist and can be reset by infrastructure changes, updates or model upgrades, and that a new chat session is recommended when follow-up answers drift. | G9: Documented behaviour on both counts: history may be lost, and because responses are automatically limited and summarized, follow-ups built on that limited context can go wrong. | I9: (manual) Confirm the user guidance covers history volatility and the new-session recommendation. [expected: documented] | J9: Add it to the user guidance and to the in-product tips where the surface allows. | K9: Users chase increasingly wrong answers down a degraded context chain. | L9: Fabric data agent creation | M9: documented | N9: unknown | T9: 3
A10: AGT-008 | B10: The underlying LLM cannot be changed - accept and design around it | C10: low | D10: limit | E10: fabric-data-agent | F10: Design decisions must not assume the ability to substitute the model behind a Fabric data agent. | G10: Documented limitation. Where model behaviour is unacceptable, the levers are schema, instructions, examples and verified answers - not the model. | I10: (manual) Confirm no architecture decision depends on model substitution. [expected: documented] | J10: Direct tuning effort at the grounding configuration instead. | K10: Effort spent on an option that does not exist. | L10: Fabric data agent creation | M10: documented | N10: unknown | T10: 1
A11: AGT-009 | B11: Agents are split by subject area rather than consolidated | C11: high | D11: config | E11: fabric-data-agent | F11: Where the question scope spans several unrelated subject areas, separate narrowly scoped agents must be used instead of one agent bound to the maximum five sources. | G11: Follows directly from the documented guidance to select only relevant objects for the question scope in order to reduce ambiguity and latency. A single wide agent must route across every bound source on every question. | I11: (manual) Review the subject-area breadth of each agent against its bound sources. [expected: agents scoped to coherent subject areas] | J11: Split by subject area; accept more agents in exchange for narrower reasoning per question. | K11: Routing errors and latency scale with source count on every question. | L11: Best practices for configuring your data agent; Semantic model best practices for data agent | M11: inferred | N11: unknown | T11: 5
A12: AGT-010 | B12: Schema object descriptions are used on the preview runtime where available | C12: medium | D12: metadata | E12: fabric-data-agent | F12: Where the preview runtime supports schema object descriptions, they must be applied to abbreviated or generic names, columns with codes, flags, units or category values, date columns tied to a business event, and objects in large schemas. | G12: Documented as a preview-runtime capability with a specific priority list for where it matters. | I12: (manual) Confirm the runtime version, then review description coverage across the priority categories. [expected: descriptions applied where supported] | J12: Apply descriptions following the documented priority order. | K12: Non-semantic-model sources reason from bare column names. | L12: Best practices for configuring your data agent | M12: documented | N12: unknown | T12: 3

Sheet Performance & query efficiency
A1: Performance & query efficiency - 8 rules, area weight 9 | J1: Fill the yellow cells only. Result must be one of: unknown, pass, partial, fail, na
A2: Rule ID | B2: Title | C2: Severity | D2: Type | E2: Applies to | F2: Requirement | G2: Why it matters | H2: Hard limit | I2: How to check | J2: Remediation | K2: If not fixed | L2: Source | M2: Basis | N2: Result | O2: Evidence / link | P2: Owner | Q2: Due date | R2: Notes | T2: _weight
A3: PRF-001 | B3: The semantic model is performance-tuned before any AI tuning begins | C3: critical | D3: performance | E3: copilot-powerbi, fabric-data-agent | F3: Semantic model performance optimization must be completed before Prep for AI configuration, and it is step one of the documented implementation workflow. | G3: Stated as the starting point: optimize the semantic model for performance first, because a well-optimized model achieves faster query execution and poor performance directly degrades the user experience. No amount of prompt tuning compensates for a model that is slow to query. | I3: (vpax) Record model size, refresh duration, and p95 query duration from a representative workload before and after AI enablement. [expected: documented performance baseline] | J3: Run the Best Practice Analyzer and the Semantic Model Memory Analyzer, fix what they surface, then start AI configuration. | K3: Every AI question inherits the model's existing slowness and multiplies it by the generator's less efficient DAX. | L3: Semantic model best practices for data agent | M3: documented | N3: unknown | T3: 8
A4: PRF-002 | B4: Best Practice Analyzer runs as a gate, not an occasional review | C4: high | D4: performance | E4: copilot-powerbi, fabric-data-agent | F4: The Best Practice Analyzer must run against every in-scope model on each release, with results triaged and material findings resolved before deployment. | G4: Named as the recommended tool for identifying incorrect data types, unnecessary columns, high cardinality columns and inefficient DAX patterns - which are precisely the conditions that make generated queries expensive. | I4: (api) Confirm BPA runs in the pipeline and review the open finding count and age. [expected: automated with triaged results] | J4: Wire BPA into the release pipeline and fail the build on the rule categories you have agreed matter. | K4: Known-bad patterns accumulate and directly inflate AI query cost. | L4: Semantic model best practices for data agent | M4: documented | N4: unknown | T4: 5
A5: PRF-003 | B5: Generated DAX is inspected for scan breadth on representative questions | C5: critical | D5: performance | E5: copilot-powerbi, fabric-data-agent | F5: For each question in the golden set, the generated DAX must be captured and reviewed for storage engine scan breadth - unfiltered fact scans, missing date filters, and full-column materialization. | G5: This is the direct measurement of the behaviour to be prevented. Reviewing the generated DAX in each response is documented practice, and scan breadth is the metric that distinguishes a targeted query from an ad-hoc full scan. | I5: (trace) Capture generated DAX and trace events per golden question. Record storage engine query count, rows scanned, and total duration. [expected: agreed scan and duration budget per question class] | J5: Where scans are broad, fix the cause: a missing default filter in instructions, a missing pre-built measure, or a missing verified answer. | K5: Exactly the ad-hoc-SQL-server behaviour - full scans returned as conversational answers, at full capacity cost. | L5: Semantic model best practices for data agent; Use Copilot with semantic models in Power BI | M5: documented | N5: unknown | T5: 16
A6: PRF-004 | B6: A latency budget exists per question class and is measured | C6: high | D6: performance | E6: copilot-powerbi, fabric-data-agent | F6: An explicit response-time budget must be set per question class and measured against real traffic. | G6: Latency is driven by schema breadth and instruction complexity, both of which are under your control. Without a budget there is no signal telling you when schema drift has started. | I6: (manual) Record p50 and p95 response time per question class against the documented budget. [expected: within budget] | J6: Where the budget is breached, narrow the AI data schema and trim instructions before considering capacity increases. | K6: Latency regressions go unnoticed until users abandon the feature. | L6: Semantic model best practices for data agent; Established semantic modeling / Copilot tuning practice (not a single Microsoft doc) | M6: inferred | N6: unknown | T6: 5
A7: PRF-005 | B7: Token cost per question is measured and budgeted | C7: critical | D7: performance | E7: fabric-data-agent | F7: Average input and output tokens per question must be measured per agent, converted to CU seconds, and tracked against a budget. | G7: Instructions, source instructions, example queries and conversation history are all billed as input tokens on every request, and output bills at four times the uncached input rate. Token growth is the mechanism by which good intentions become an unaffordable AI surface. | I7: (metrics) From Capacity Metrics AI Query operations, derive average input and output tokens per request and the resulting CU seconds. Track the trend. [expected: within documented per-question CU budget] | J7: Trim instructions and examples, exploit cached input where prompt prefixes are stable - cached input is billed at a tenth of the uncached rate - and shift recurring questions to verified answers. | K7: Per-question cost drifts upward invisibly until the capacity throttles. | L7: Data agent consumption | M7: documented | N7: unknown | T7: 8
A8: PRF-006 | B8: Prompt prefix stability is preserved to benefit from cached input pricing | C8: medium | D8: performance | E8: fabric-data-agent | F8: Instructions and example queries should be kept stable between requests so that cached input pricing applies. | G8: Cached input bills at 10 CU seconds per 1,000 tokens against 100 for uncached - a tenfold difference on the largest and most repetitive part of every request. | I8: (manual) Confirm instruction and example content is not rewritten per request or per user, and review the observed cached-versus-uncached token mix. [expected: stable prompt prefix] | J8: Avoid dynamic per-user instruction injection; put variability in the question, not the prefix. | K8: Up to ten times the necessary input token cost on every request. | L8: Data agent consumption | M8: documented | N8: unknown | T8: 3
A9: PRF-007 | B9: Aggregation-first answering is the instructed default | C9: high | D9: performance | E9: fabric-data-agent, copilot-powerbi | F9: Instructions must direct the agent to aggregate, rank or top-N by default rather than returning detail rows, unless the user explicitly asks for detail. | G9: Combines the documented 25 row by 25 column response cap with documented default-filter guidance. Detail-row answers are simultaneously the most expensive to produce and the most likely to be silently truncated. | I9: (manual) Review instructions for an aggregation-first default and confirm the behaviour on detail-seeking golden questions. [expected: aggregation-first default stated] | J9: State it explicitly, and have the agent name the aggregation it chose so users can challenge it. | K9: Wide, expensive result sets truncated to 25 rows and presented as complete. | L9: Fabric data agent creation; Best practices for configuring your data agent | M9: inferred | N9: unknown | T9: 5
A10: PRF-008 | B10: AI-driven capacity events are correlated with AI usage | C10: high | D10: performance | E10: copilot-powerbi, fabric-data-agent | F10: Throttling and overload events on AI-enabled capacities must be investigated with AI Query consumption included in the correlation. | G10: Copilot consumes the same capacity as everything else and overconsumption can throttle unrelated Fabric operations. Once capacity is exhausted all operations shut down, so the incident presents as a refresh failure rather than an AI problem. | I10: (metrics) For each throttling event, record whether AI Query consumption was examined as a contributing factor. [expected: AI included in incident analysis] | J10: Add AI Query to the standard capacity incident runbook. | K10: Repeated incidents misattributed to refresh scheduling while the real driver is AI adoption. | L10: Overview of Copilot in Fabric; Data agent consumption | M10: documented | N10: unknown | T10: 5

Sheet Response validity & relevance
A1: Response validity & relevance - 13 rules, area weight 10 | J1: Fill the yellow cells only. Result must be one of: unknown, pass, partial, fail, na
A2: Rule ID | B2: Title | C2: Severity | D2: Type | E2: Applies to | F2: Requirement | G2: Why it matters | H2: Hard limit | I2: How to check | J2: Remediation | K2: If not fixed | L2: Source | M2: Basis | N2: Result | O2: Evidence / link | P2: Owner | Q2: Due date | R2: Notes | T2: _weight
A3: VAL-001 | B3: A golden question set exists with expected answers | C3: blocker | D3: validation | E3: copilot-powerbi, fabric-data-agent | F3: Each model or agent in scope must have a maintained golden question set with agreed correct answers, covering the declared question scope including edge cases and known-ambiguous phrasings. | G3: Validation and iteration is a documented workflow step, and the accelerator guidance is explicit that retrieval and generation must be evaluated and tuned before production use. Without a fixed question set with known answers, there is nothing to tune against and no way to detect regression. | I3: (manual) Confirm a golden set exists, covers the declared scope, has agreed expected answers, and has been run within the last release cycle. [expected: current golden set with expected answers] | J3: Build it from real user questions, agree the correct answer with the business data owner, and version it alongside the model. | K3: Quality is anecdotal, regressions are invisible, and every tuning decision is a guess. | L3: Semantic model best practices for data agent; chat-with-your-data-solution-accelerator - best practices; microsoft/rag-experiment-accelerator | M3: documented | N3: unknown | T3: 26
A4: VAL-002 | B4: Answer accuracy is scored against the golden set each release | C4: critical | D4: validation | E4: copilot-powerbi, fabric-data-agent | F4: Every release must score the golden question set and record the pass rate, with a defined minimum for promotion to production. | G4: Establishes the regression gate. The accelerators' evaluation discipline - measure, tune configuration, re-measure - is directly transferable even though the retrieval mechanics differ. | I4: (manual) Record pass rate per release and compare against the promotion threshold. [gte 90 percent of golden questions correct (recommended promotion gate)] | J4: Gate promotion on the threshold. The 90 percent figure is a working default to be calibrated to your risk appetite, not a Microsoft-published number. | K4: Model or configuration changes silently degrade answers between releases. | L4: chat-with-your-data-solution-accelerator - best practices; microsoft/rag-experiment-accelerator; Established semantic modeling / Copilot tuning practice (not a single Microsoft doc) | M4: inferred | N4: unknown | T4: 16
A5: VAL-003 | B5: Answer relevance is scored separately from accuracy | C5: high | D5: validation | E5: copilot-powerbi, fabric-data-agent | F5: Responses must be scored for relevance - did the answer address the question asked - separately from numeric correctness. | G5: The RAG evaluation vocabulary separates answer relevance from correctness for good reason: an answer can be arithmetically right and still not respond to what was asked, and the two failures have entirely different fixes. | I5: (manual) Score each golden response on a relevance scale in addition to the correctness pass or fail. Track the two independently. [expected: relevance threshold agreed and met] | J5: Relevance failures point at instructions and terminology mapping; correctness failures point at the model and measures. Route each to the right fix. | K5: Tuning effort aimed at the wrong layer. | L5: microsoft/rag-experiment-accelerator; Azure-Samples/chat-with-your-data-solution-accelerator; chat-with-your-data-solution-accelerator - best practices | M5: inferred | N5: unknown | T5: 5
A6: VAL-004 | B6: Grounding sufficiency is scored - context precision and recall | C6: critical | D6: validation | E6: copilot-powerbi, fabric-data-agent | F6: Each golden question must be scored for whether the AI-visible schema contained everything needed to answer it and nothing that misled it. | G6: Adapted from context precision and context recall. In a natural-language-to-DAX setting the retrieved context is the AI data schema, so precision means the schema was not cluttered with distractors, and recall means nothing required was trimmed away. This is the direct measurement of whether schema reduction has gone too far or not far enough. | I6: (manual) For each failed golden question, classify the cause as missing schema object (recall failure), distracting schema object (precision failure), or generation error. Track the three counts. [expected: failure causes classified] | J6: Recall failures mean adding back a specific object. Precision failures mean removing one. Generation errors mean a verified answer or a pre-built measure. Never respond to a failure by widening the schema generally. | K6: Schema is widened reflexively after every failure, which is how models drift back to scanning everything. | L6: microsoft/rag-experiment-accelerator; Established semantic modeling / Copilot tuning practice (not a single Microsoft doc) | M6: inferred | N6: unknown | T6: 16
A7: VAL-005 | B7: Generated DAX is reviewed for every golden question, not just the result | C7: critical | D7: validation | E7: copilot-powerbi, fabric-data-agent | F7: Validation must inspect the generated DAX query in each response, not only whether the returned number looks right. | G7: Stated as a direct requirement: accuracy depends on the generated DAX being correct, and when results are wrong the DAX is what tells you which configuration layer to adjust. A right answer from wrong DAX is a coincidence that will not survive the next question. | I7: (manual) Capture and review generated DAX per golden question; confirm filter context, relationship usage and measure selection are correct. [expected: DAX reviewed per golden question] | J7: Where the DAX is wrong, identify whether the fix belongs in the model, the AI data schema, verified answers or AI instructions. | K7: Coincidentally correct answers that fail on the next variation of the same question. | L7: Semantic model best practices for data agent | M7: documented | N7: unknown | T7: 16
A8: VAL-006 | B8: Non-determinism is measured by repeat testing | C8: high | D8: validation | E8: copilot-powerbi, fabric-data-agent | F8: A subset of golden questions must be asked repeatedly to measure answer variance across runs. | G8: The model is documented as nondeterministic - the same prompt on the same model may produce different results. Variance is a measurable quality attribute and the strongest argument for verified answers on high-consequence questions. | I8: (manual) Run a sample of questions several times and record the proportion returning materially different answers. [expected: variance within agreed tolerance] | J8: For every high-consequence question showing variance, create a verified answer. That converts a probabilistic answer into a deterministic one. | K8: Two executives ask the same question and get different numbers, which ends the programme. | L8: Use Copilot with semantic models in Power BI; Copilot in Power BI tutorial: prepare a semantic model for AI | M8: documented | N8: unknown | T8: 5
A9: VAL-007 | B9: Numeric answers carry a review expectation | C9: high | D9: governance | E9: copilot-powerbi, fabric-data-agent | F9: User guidance must state that AI-generated numeric answers are to be verified against the source report or model before being relied upon for decisions. | G9: Both the Microsoft guidance and the accelerator guidance say this plainly: inaccurate responses lead to incorrect decisions, and numeric answers should be reviewed against sources. The accelerator adds that its stack is optimized for unstructured data and numeric answers deserve particular scepticism. | I9: (manual) Confirm the expectation appears in user-facing guidance and in onboarding material. [expected: documented and communicated] | J9: State it in onboarding and, where the surface allows, alongside the answer itself. | K9: Unverified AI numbers enter decisions and reports. | L9: Use Copilot with semantic models in Power BI; chat-with-your-data-solution-accelerator - best practices | M9: documented | N9: unknown | T9: 5
A10: VAL-008 | B10: Question scope breadth is matched to schema breadth | C10: medium | D10: governance | E10: copilot-powerbi, fabric-data-agent | F10: The declared question scope must be proportionate to the AI-visible schema: a narrow schema requires a narrow, well-communicated question scope. | G10: The accelerator states the tradeoff directly - the more limited the data set, the broader the questions should be, and more depth requires more available data. Scope reduction is not free; it must be paired with honest communication about what the surface can answer. | I10: (manual) Compare the published question scope against the AI-visible schema and confirm they are consistent. [expected: scope and schema aligned and published] | J10: Publish what the surface can and cannot answer, and route out-of-scope questions explicitly rather than answering them badly. | K10: Users ask beyond the schema and receive confident, unsupported answers. | L10: chat-with-your-data-solution-accelerator - best practices | M10: documented | N10: unknown | T10: 3
A11: VAL-009 | B11: Precision targets are set deliberately per question class | C11: medium | D11: governance | E11: copilot-powerbi, fabric-data-agent | F11: The required precision must be agreed per question class, recognising that higher precision requirements make a response harder to generate at all. | G11: Documented tuning guidance: tune prompt configuration to the level of precision required, and the more precision desired the harder it may be to generate a response. Demanding uniform maximum precision produces refusals and non-answers. | I11: (manual) Confirm question classes carry differentiated precision expectations. [expected: per-class precision targets] | J11: Reserve strict precision for financial and regulatory questions; allow exploratory questions to be directional. | K11: Either dangerous imprecision on regulated numbers or a system that refuses to answer exploratory questions. | L11: chat-with-your-data-solution-accelerator - best practices | M11: documented | N11: unknown | T11: 3
A12: VAL-010 | B12: Configuration changes are evaluated as controlled experiments | C12: critical | D12: validation | E12: copilot-powerbi, fabric-data-agent | F12: Changes to AI data schema, instructions, examples or verified answers must be evaluated by re-running the golden set and comparing scores against the prior configuration, one variable at a time where practical. | G12: This is the core method of the RAG Experiment Accelerator - sweep the tunable parameters, measure with a fixed metric set, keep what improves the score - and the shape the Chat with your data accelerator gives it, where chunking, retrieval type and prompt configuration are an explicit admin surface meant to be tuned against your own data rather than shipped at defaults. The tunable surface here is different (schema breadth, instruction content, example count, verified answer coverage) but the discipline transfers exactly. | I12: (manual) Confirm each configuration change has a before-and-after golden set score recorded against it. [expected: experiment record per change] | J12: Keep a tuning log: configuration version, what changed, accuracy, relevance, latency, tokens per question. Revert changes that do not earn their place. | K12: Configuration accretes on intuition; nobody can say which settings are actually helping and none can safely be removed. | L12: microsoft/rag-experiment-accelerator; Azure-Samples/chat-with-your-data-solution-accelerator; chat-with-your-data-solution-accelerator - best practices | M12: inferred | N12: unknown | T12: 16
A13: VAL-011 | B13: User feedback is captured and routed into the tuning backlog | C13: high | D13: operations | E13: copilot-powerbi, fabric-data-agent | F13: Thumbs up and down feedback must be collected, reviewed on a defined cadence, and converted into schema, instruction or verified answer changes. | G13: Feedback via the thumbs controls is part of the documented testing loop. Feedback that is collected but never actioned is worse than none, because it signals responsiveness that does not exist. | I13: (manual) Confirm feedback is reviewed on a cadence with a named owner, and that items trace to configuration changes. [expected: active feedback loop] | J13: Review negative feedback each sprint, classify by the VAL-004 failure taxonomy, and act on the classification. | K13: The strongest available signal about real-world quality is discarded. | L13: Copilot in Power BI tutorial: prepare a semantic model for AI | M13: documented | N13: unknown | T13: 5
A14: VAL-012 | B14: Copilot-generated visual filters are understood as potentially misleading | C14: medium | D14: validation | E14: copilot-powerbi | F14: Reviewers must check whether visuals generated by Copilot carry visual-level filters that a user could not create manually, and communicate this risk. | G14: Documented limitation: Copilot-generated visuals may contain visual-specific filters users cannot create manually, which can be misleading. A visual that cannot be reproduced by hand cannot be independently verified by the user looking at it. | I14: (manual) Inspect the filter pane on Copilot-generated visuals during golden set review. [expected: reviewed] | J14: Flag the behaviour in user guidance and treat unreproducible visuals as a reason to build a verified answer instead. | K14: Users act on a chart whose filtering they cannot see or reproduce. | L14: Use Copilot with semantic models in Power BI | M14: documented | N14: unknown | T14: 3
A15: VAL-013 | B15: Answers are known to be ephemeral and are not treated as reports | C15: low | D15: governance | E15: copilot-powerbi | F15: User guidance must state that Copilot answers are static and disappear when the pane closes, so anything needed repeatedly belongs in a report or a verified answer. | G15: Documented behaviour. It also has a cost consequence: users who re-ask the same question daily because there is nowhere to save the answer are paying full generation cost each time. | I15: (manual) Confirm the guidance covers ephemerality and directs recurring needs to reports or verified answers. [expected: documented] | J15: Track repeatedly asked questions and promote them into reports or verified answers. | K15: Recurring questions regenerated indefinitely at full cost. | L15: Use Copilot with semantic models in Power BI | M15: documented | N15: unknown | T15: 1

Sheet Operations, ALM & adoption
A1: Operations, ALM & adoption - 7 rules, area weight 6 | J1: Fill the yellow cells only. Result must be one of: unknown, pass, partial, fail, na
A2: Rule ID | B2: Title | C2: Severity | D2: Type | E2: Applies to | F2: Requirement | G2: Why it matters | H2: Hard limit | I2: How to check | J2: Remediation | K2: If not fixed | L2: Source | M2: Basis | N2: Result | O2: Evidence / link | P2: Owner | Q2: Due date | R2: Notes | T2: _weight
A3: OPS-001 | B3: AI configuration is under source control | C3: high | D3: operations | E3: copilot-powerbi, fabric-data-agent | F3: AI data schema, AI instructions and verified answers must be held in source control and deployed through deployment pipelines. | G3: Implementing source control and deployment pipelines is the final documented step of the workflow. AI configuration is production configuration and deserves the same handling as model code. | I3: (manual) Confirm the AI configuration is committed to source control and deployed through a pipeline rather than edited directly in production. [expected: under source control] | J3: Bring Prep for AI configuration into the repository with the model definition, and remember the post-deployment refresh required by SCH-018. | K3: Production AI behaviour that nobody can reconstruct, review or roll back. | L3: Semantic model best practices for data agent; Prepare your data for AI to improve Copilot results (preview) | M3: documented | N3: unknown | T3: 5
A4: OPS-002 | B4: Adoption and usage are measured, not assumed | C4: high | D4: operations | E4: copilot-powerbi, fabric-data-agent | F4: Active users, questions per user, question volume by model or agent, and abandonment must be measured and reviewed. | G4: Enablement without usage measurement cannot tell success from silence, and usage also drives the 14-day activity window that keeps instance value indexes fresh. | I4: (metrics) Report active users, questions per user and volume by item over the period. [expected: reported on a cadence] | J4: Add AI usage to the platform reporting pack alongside report usage. | K4: No basis for investment decisions and no early warning of abandonment. | L4: Established semantic modeling / Copilot tuning practice (not a single Microsoft doc); Frequently asked questions about preparing data for AI | M4: inferred | N4: unknown | T4: 5
A5: OPS-003 | B5: A named owner exists per AI-enabled model and agent | C5: high | D5: governance | E5: copilot-powerbi, fabric-data-agent | F5: Every AI-enabled semantic model and every data agent must have a named business owner and a named technical owner. | G5: Unapproved models direct users to contact the content owner. If there is no owner, that instruction is a dead end and quality issues have nowhere to go. | I5: (manual) Confirm both owners are recorded per item in the register and are current. [expected: owners recorded] | J5: Assign owners as a precondition of AI enablement. | K5: Quality issues raised by users go unaddressed and trust decays. | L5: Copilot in Power BI tutorial: prepare a semantic model for AI; Established semantic modeling / Copilot tuning practice (not a single Microsoft doc) | M5: inferred | N5: unknown | T5: 5
A6: OPS-004 | B6: This assessment is re-run on a defined cadence | C6: high | D6: governance | E6: copilot-powerbi, fabric-data-agent | F6: The assessment must be re-run at a defined cadence and on any material model, agent or platform change, with results trended over time. | G6: Every control in this pack decays. Schemas widen, descriptions go stale after renames, instructions accrete, and the platform itself changes underneath - Q&A retirement being a dated example. | I6: (manual) Confirm the cadence is defined, the last run date is within it, and scores are trended. [expected: current assessment with trend] | J6: Schedule it quarterly at minimum, and trigger it on major model or platform changes. | K6: A one-off assessment that describes a state the estate left months ago. | L6: Established semantic modeling / Copilot tuning practice (not a single Microsoft doc) | M6: inferred | N6: unknown | T6: 5
A7: OPS-005 | B7: Responsible AI guidance is published to users | C7: medium | D7: governance | E7: copilot-powerbi, fabric-data-agent | F7: User-facing guidance must cover validation expectations, non-determinism, the limits of the question scope, and how to report a wrong answer. | G7: Responsible use guidance is emphasised in both the Microsoft documentation and the accelerator guidance, which states plainly that AI-generated content may be incorrect and should be reviewed before use. | I7: (manual) Confirm the guidance exists, is published where users encounter the AI surface, and covers the four topics. [expected: published] | J7: Publish it at the point of use rather than burying it in a policy document. | K7: Users with no framework for judging or challenging AI output. | L7: Copilot in Power BI tutorial: prepare a semantic model for AI; chat-with-your-data-solution-accelerator - best practices | M7: documented | N7: unknown | T7: 3
A8: OPS-006 | B8: Data reachable by AI is reviewed against the access model | C8: critical | D8: security | E8: copilot-powerbi, fabric-data-agent | F8: Before a source is exposed to an AI surface, confirm that its contents are appropriate for every user who can reach that surface, given the effective permission model. | G8: The accelerator states the blunt version - only upload data that can be accessed by any user of the application. Fabric's model is more nuanced because RLS and user identity flow through, but the discipline is the same: enumerate who can reach the surface and confirm the content suits the widest reader. | I8: (manual) For each AI surface, enumerate the effective audience and confirm a content suitability review has been recorded. [expected: review recorded per surface] | J8: Where content is not suitable for the widest reader, either narrow the audience or enforce RLS and re-test through the AI path per SEC-002. | K8: Conversational access materially widens the effective reach of sensitive content. | L8: chat-with-your-data-solution-accelerator - best practices; Established semantic modeling / Copilot tuning practice (not a single Microsoft doc) | M8: documented | N8: unknown | T8: 8
A9: OPS-007 | B9: Timeout and error behaviour is monitored | C9: medium | D9: operations | E9: copilot-powerbi | F9: Copilot timeouts and errors, including failures to fetch the LSDL, must be monitored and investigated rather than treated as user error. | G9: Documented behaviour: Copilot capabilities might time out in rare circumstances because the LSDL cannot be fetched, and responses may time out where the model, DAX or data is too complex. A rising timeout rate is a leading indicator of schema and complexity drift. | I9: (manual) Track timeout and error rate per model over time. [expected: within agreed threshold and not trending upward] | J9: Investigate rising timeouts as a schema breadth or model complexity problem first. | K9: A measurable early warning of degradation is discarded as noise. | L9: Prepare your data for AI to improve Copilot results (preview); Use Copilot with semantic models in Power BI | M9: documented | N9: unknown | T9: 3

Sheet All rules
A1: All rules - flat reference. Score on the area tabs, not here.
A2: Rule ID | B2: Title | C2: Severity | D2: Type | E2: Applies to | F2: Requirement | G2: Why it matters | H2: Hard limit | I2: How to check | J2: Remediation | K2: If not fixed | L2: Source | M2: Basis | N2: Result | O2: Evidence / link | P2: Owner | Q2: Due date | R2: Notes
A3: ORG-001 | B3: EXAMPLE ROW - delete before use: your own added rule | C3: high | D3: config | E3: copilot-powerbi | F3: What must be true. | G3: Why it matters for answer quality or cost. | H3: e.g. 200 characters (hard) | I3: (manual) How to gather the evidence. | J3: What to do about it. | K3: What goes wrong if you don't. | L3: Your standard | M3: inferred | N3: pass | O3: link to evidence | P3: data.platform@contoso | Q3: 2026-10-31 | R3: free text
A4: TEN-001 | B4: Copilot / Azure OpenAI tenant switch is enabled for the intended audience | C4: blocker | D4: enablement | E4: copilot-powerbi, fabric-data-agent | F4: The tenant setting 'Users can use Copilot and other features powered by Azure OpenAI' must be enabled, scoped either to the whole organization or to the specific security groups that are in scope for AI. | G4: This is the master switch. Every downstream Copilot and data agent experience depends on it. | I4: (admin-portal) Fabric Admin Portal > Tenant settings > Copilot and Agent. Record state and the security groups it is scoped to. [expected: enabled] | J4: Enable the setting and scope it to the AI pilot security group rather than the entire organization, so that usage and capacity burn stay attributable during rollout. | K4: No Copilot or data agent functionality at all. | L4: Enable Fabric Copilot for Power BI; Copilot and Agent admin settings; Configure Fabric data agent tenant settings | M4: documented | N4: unknown | R4: Microsoft docs are inconsistent on the default state of this switch: the Copilot and Agent admin settings page and the Power BI enablement page describe it as enabled by default, while the data agent tenant settings page lists it as off. Do not assume - read the actual tenant state and record it as evidence.
A5: TEN-002 | B5: Cross-geo processing switch matches the capacity's region | C5: blocker | D5: enablement | E5: copilot-powerbi, fabric-data-agent | F5: If the Fabric capacity is outside the US regions and the EU Data Boundary, the tenant setting 'Data sent to Azure OpenAI can be processed outside your capacity's geographic region, compliance boundary, or national cloud instance' must be enabled, and that decision must be signed off by the data-residency owner. | G5: Azure OpenAI is deployed in US datacenters and the EU Data Boundary only. UK capacities route to the EU boundary; Australia, Brazil, Canada, India, Asia, Japan, Korea, South Africa, Southeast Asia and UAE route to the US. Without the switch, Copilot simply does not work in those regions. | I5: (admin-portal) Determine the capacity's region, then check the cross-geo processing tenant setting. Record both, plus the residency sign-off reference. [expected: enabled when capacity region is outside US and EU Data Boundary] | J5: Either enable cross-geo processing with documented residency approval, or relocate the capacity into a region where Azure OpenAI is served locally. | K5: Copilot requests fail in-region; users experience errors rather than degraded answers. | L5: Overview of Copilot in Fabric; Copilot and Agent admin settings | M5: documented | N5: unknown
A6: TEN-003 | B6: Cross-geo storage and conversation-history switches are a deliberate decision | C6: high | D6: governance | E6: fabric-data-agent, copilot-notebooks | F6: For tenants outside the EU Data Boundary and US, the settings 'Data sent to Azure OpenAI can be stored outside...' and 'Conversation history stored outside your capacity's geographic region...' must be explicitly decided - enabled with residency approval, or accepted as disabled with the loss of multi-session context understood. | G6: Conversation history is what gives agentic experiences memory across sessions; it is retained 28 days unless a user deletes it. Leaving these off outside EU/US silently degrades multi-turn quality. | H6: 28 days (hard) | I6: (admin-portal) Record both switch states and the documented decision. Both default to disabled. [expected: documented decision] | J6: Record the decision in the AI governance register. If disabled, set user expectations that each session starts cold. | K6: Agents lose cross-session context; users repeat themselves and blame the agent for forgetting. | L6: Copilot and Agent admin settings; Configure Fabric data agent tenant settings; Overview of Copilot in Fabric | M6: documented | N6: unknown
A7: TEN-004 | B7: 'Only show approved items in the standalone Copilot' is enabled once an approval process exists | C7: critical | D7: governance | E7: copilot-powerbi | F7: Once the organization has a working 'Approved for Copilot' review process, the tenant setting 'Only show approved items in the standalone Copilot in Power BI experience' should be enabled so standalone Copilot searches only curated content. | G7: This is the single most effective lever against the ad-hoc-scan behaviour: it stops standalone Copilot from ranging across every semantic model in the tenant and restricts it to models that have actually been prepared for AI. | I7: (admin-portal) Check the tenant setting state, and confirm at least one model has been marked Approved for Copilot. [expected: enabled] | J7: Stand up the approval review first (see WSP-004), then flip this switch. Enabling it with zero approved items makes standalone Copilot return nothing. | K7: Standalone Copilot searches unprepared models and produces confident answers from models nobody has validated. | L7: Copilot and Agent admin settings; Enable Fabric Copilot for Power BI | M7: documented | N7: unknown
A8: TEN-005 | B8: Standalone Copilot experience switch state is intentional | C8: high | D8: governance | E8: copilot-powerbi | F8: The setting 'Users can access a standalone, cross-item Copilot in Power BI experience' must be explicitly set on or off with a recorded rationale, not left at whatever the default happens to be. | G8: Standalone Copilot has the broadest blast radius of any Copilot surface because it is not anchored to one report. It also depends on the parent Azure OpenAI switch and is unavailable in Spain Central, Qatar, India-West and Mexico. | I8: (admin-portal) Record switch state, target groups, and the rationale. Confirm the tenant home region is not one of the unsupported regions. [expected: documented decision] | J8: Keep it off until model preparation and approval reach Optimized maturity, then enable narrowly. | K8: Broad, ungrounded question surface exposed before models are ready. | L8: Copilot and Agent admin settings; Prepare your data for AI to improve Copilot results (preview) | M8: documented | N8: unknown
A9: TEN-006 | B9: Fabric Copilot capacity designation is configured for cost attribution | C9: high | D9: governance | E9: copilot-powerbi, fabric-data-agent | F9: If Copilot cost needs to be isolated from analytical workloads, the setting 'Capacities can be designated as Copilot in Fabric capacities' must be enabled and a dedicated Copilot capacity assigned. | G9: Copilot consumes the same CU pool as everything else. A dedicated Copilot capacity consolidates AI billing and prevents AI spikes from throttling refreshes and report queries. | I9: (admin-portal) Check the tenant setting, then check whether a capacity is designated and which users or groups are assigned to it. [expected: designated capacity or documented decision not to] | J9: Designate a Copilot capacity and assign the AI audience to it, so AI Query operations are separately visible in the Capacity Metrics app. | K9: AI consumption is indistinguishable from BI consumption; throttling incidents cannot be attributed. | L9: Copilot and Agent admin settings; Configure Fabric data agent tenant settings; Enable Fabric Copilot for Power BI | M9: documented | N9: unknown
A10: TEN-007 | B10: Capacity-level Copilot delegation is reviewed, not just tenant settings | C10: high | D10: governance | E10: copilot-powerbi, fabric-data-agent | F10: Delegated tenant settings on each in-scope capacity must be reviewed, because a capacity administrator can enable Copilot at capacity level even where it is disabled at tenant level. | G10: Reviewing only the tenant page gives a false sense of control. Cross-geo delegation notably does not auto-delegate and must be set per capacity. | I10: (admin-portal) Admin Portal > Capacity settings > each capacity > Delegated tenant settings. Record any capacity that overrides the tenant position. [expected: per-capacity review record] | J10: Audit every capacity's delegated settings and reconcile overrides against the intended tenant policy. | K10: Shadow Copilot enablement on capacities the AI governance team does not know about. | L10: Enable Fabric Copilot for Power BI | M10: documented | N10: unknown
A11: TEN-008 | B11: Purview DLP and access-restriction policies are evaluated for AI surfaces | C11: critical | D11: governance | E11: fabric-data-agent | F11: Where the tenant is governed by Microsoft Purview, DLP policies for Fabric Data Warehouse and access-restriction policies for KQL Database, SQL Database and Data Warehouse must be reviewed against the data an agent can reach. | G11: An agent inherits the user's read access; Purview policies are the layer that prevents an otherwise-authorized query from surfacing regulated content in a chat response. | I11: (manual) List agent data sources, then confirm each has been assessed against active Purview DLP and access-restriction policies. [expected: assessment record per data source] | J11: Run a Purview policy review as part of agent intake; block sources that carry regulated data without a policy. | K11: Regulated data surfaced conversationally with no DLP interception. | L11: Fabric data agent creation | M11: documented | N11: unknown
A12: TEN-009 | B12: Tenant setting changes are allowed an hour to propagate before troubleshooting | C12: low | D12: governance | E12: copilot-powerbi, fabric-data-agent | F12: The runbook must state that Copilot and data agent tenant settings can take up to one hour to take effect, and that troubleshooting should not begin before that window elapses. | G12: Most 'Copilot is broken after we enabled it' escalations are impatience. Codifying the wait prevents wasted support cycles and premature setting churn. | H12: 1 hours (soft) | I12: (manual) Confirm the enablement runbook documents the propagation delay. [expected: documented in runbook] | J12: Add the one-hour propagation note to the enablement runbook and the support script. | K12: Settings toggled repeatedly during the propagation window, confusing the audit trail. | L12: Configure Fabric data agent tenant settings | M12: documented | N12: unknown
A13: CAP-001 | B13: Capacity meets the minimum paid SKU | C13: blocker | D13: limit | E13: copilot-powerbi, fabric-data-agent | F13: Every workspace hosting a Copilot-enabled model or a data agent must be on a paid Fabric capacity of F2 or higher, or Power BI Premium P1 or higher with Fabric enabled. | G13: Trial SKUs are not supported for Azure OpenAI access. This is a hard gate, not a performance recommendation. | H13: F2 / P1 sku (hard) | I13: (api) Enumerate in-scope workspaces and their assigned capacity SKU. Flag any on trial, PPU-only, or shared capacity. [gte F2] | J13: Move the workspace to a qualifying paid capacity, or assign users to a Fabric Copilot capacity. | K13: Copilot and data agent features are unavailable regardless of tenant settings. | L13: Fabric data agent creation; Overview of Copilot in Fabric; Use Copilot with semantic models in Power BI | M13: documented | N13: unknown
A14: CAP-002 | B14: Capacity region is supported and consistent across agent and sources | C14: blocker | D14: limit | E14: fabric-data-agent | F14: The data agent's workspace capacity and every data source workspace capacity must be in the same region, and that region must be one where Fabric AI workloads are available. | G14: Cross-region source binding fails outright - a Lakehouse on North Europe capacity will not serve an agent whose capacity is in France Central. Sovereign clouds are not supported at all. | I14: (api) For each agent, list the region of its own capacity and of every bound data source's capacity. All must match. [expected: identical region across agent and all sources] | J14: Relocate either the agent workspace or the source workspaces so all sit on same-region capacity. | K14: Agent creation or query execution fails against the mismatched source. | L14: Fabric data agent creation; Overview of Copilot in Fabric | M14: documented | N14: unknown
A15: CAP-003 | B15: AI Query consumption is monitored in the Capacity Metrics app | C15: critical | D15: performance | E15: fabric-data-agent, copilot-powerbi | F15: AI Query operations and the LlmPlugin item kind must be actively monitored in the Fabric Capacity Metrics app, with a named owner and a review cadence. | G15: Data agent requests bill at 100 CU seconds per 1,000 input tokens, 10 CU seconds per 1,000 cached input tokens, and 400 CU seconds per 1,000 output tokens - and the generated SQL/DAX/KQL is billed separately to its own engine on top. Without monitoring, a verbose instruction set silently multiplies cost on every single question. | H15: inputPer1kTokens=100; cachedInputPer1kTokens=10; outputPer1kTokens=400 CU seconds (hard) | I15: (metrics) Capacity Metrics app, filter to AI Query operations and the LlmPlugin item kind. Confirm a monitoring owner and cadence exist. [expected: monitored with named owner] | J15: Add AI Query to the capacity review pack; alert on week-over-week growth and on the ratio of output to input tokens. | K15: Unbounded AI spend and eventual capacity-wide throttling that takes refreshes down with it. | L15: Data agent consumption | M15: documented | N15: unknown
A16: CAP-004 | B16: Throttling risk from AI workloads is assessed against the SKU | C16: high | D16: performance | E16: fabric-data-agent, copilot-powerbi | F16: Expected peak AI request volume must be modelled against the capacity's daily CU budget, and the result recorded, before broad rollout. | G16: Data agent operations run as background jobs which smooth peaks, but once capacity is exhausted all operations shut down - not just AI. An F64 carrying 1,536 CU hours per day supports on the order of 13,800 requests per day before exhaustion; that number falls fast as instructions and conversation history grow. | I16: (manual) Record the SKU, its daily CU hours, the modelled average tokens per request, and the derived request ceiling. Compare against forecast adoption. [expected: documented headroom model] | J16: Model it explicitly, then either size the capacity for the forecast or cap the audience until instruction and schema trimming brings per-request tokens down. | K16: AI adoption success takes down unrelated Fabric workloads on the same capacity. | L16: Data agent consumption | M16: documented | N16: unknown
A17: CAP-005 | B17: Private Link and closed-network constraints are checked | C17: critical | D17: limit | E17: copilot-powerbi, fabric-data-agent | F17: Confirm that in-scope capacities do not depend on Private Link or closed-network configurations that are unsupported for Copilot. | G17: Copilot is not supported behind Private Link or closed networks. Discovering this after a rollout announcement is expensive. | I17: (admin-portal) Check tenant and workspace networking configuration for Private Link / closed-network enforcement. [expected: not enforced for AI-enabled workspaces] | J17: Carve the AI-enabled workspaces out of the Private Link enforcement scope, or accept that Copilot is unavailable there. | K17: Copilot silently unavailable despite every switch appearing correct. | L17: Enable Fabric Copilot for Power BI | M17: documented | N17: unknown
A18: CAP-006 | B18: Workspace outbound access protection boundaries are understood for agents | C18: medium | D18: governance | E18: fabric-data-agent | F18: Where workspace outbound access protection is in force, the permitted external endpoints must be documented and confirmed sufficient for the agent's data sources. | G18: Agents operate inside the workspace outbound access protection boundary; an administrator's endpoint allowlist directly determines what the agent can reach. | I18: (manual) Record outbound access protection state and the allowlisted endpoints for each agent workspace. [expected: documented] | J18: Reconcile the endpoint allowlist with the agent's bound sources before go-live. | K18: Intermittent, hard-to-diagnose source failures. | L18: Fabric data agent creation | M18: documented | N18: unknown
A19: WSP-001 | B19: AI-enabled workspaces are an explicit, enumerated set | C19: critical | D19: governance | E19: copilot-powerbi, fabric-data-agent | F19: There must be a maintained register of which workspaces are in scope for Copilot and data agents, rather than AI being implicitly available wherever capacity happens to be assigned. | G19: Scope control is the foundation of every other rule in this pack. You cannot tune what you have not bounded. | I19: (manual) Confirm a register exists, is current within the last quarter, and names an owner per workspace. [expected: current register] | J19: Publish the register and review it at each capacity review. | K19: AI surface expands invisibly; assessment results go stale immediately. | L19: Established semantic modeling / Copilot tuning practice (not a single Microsoft doc) | M19: inferred | N19: unknown
A20: WSP-002 | B20: Copilot cannot be enabled per workload - the audience decision is all-or-nothing | C20: high | D20: governance | E20: copilot-powerbi, fabric-data-agent | F20: The rollout plan must account for the fact that enabling Copilot in a capacity for a user or security group grants that group all Copilot workloads and experiences; it cannot be enabled for one experience only. | G20: Teams frequently plan a 'Copilot for Power BI only' pilot that is not technically achievable. The control point is the audience, not the workload. | I20: (manual) Confirm the rollout plan controls exposure by security group and capacity assignment, not by workload selection. [expected: audience-based scoping] | J20: Rewrite the rollout plan around security groups and dedicated capacities. | K20: Users reach Copilot experiences over unprepared workloads that were never in the pilot scope. | L20: Use Copilot with semantic models in Power BI | M20: documented | N20: unknown
A21: WSP-003 | B21: Staging, development and sandbox workspaces are excluded from AI capacity | C21: high | D21: governance | E21: copilot-powerbi | F21: Development, staging and personal sandbox workspaces must not sit on capacity where Copilot is enabled for business users. | G21: Half-built models with placeholder measures and unhidden technical columns are exactly the content that teaches users not to trust Copilot. | I21: (api) Cross-reference the workspace register against capacity assignment; flag any dev/test workspace on a Copilot-enabled capacity accessible to business users. [expected: no dev/test workspaces exposed] | J21: Move non-production workspaces to a separate capacity or restrict the Copilot security group to production workspace members. | K21: Users get answers from unfinished models and lose confidence permanently. | L21: Established semantic modeling / Copilot tuning practice (not a single Microsoft doc); Best practices for configuring your data agent | M21: inferred | N21: unknown
A22: WSP-004 | B22: 'Approved for Copilot' is applied through a real review, not by default | C22: critical | D22: governance | E22: copilot-powerbi | F22: Every semantic model marked 'Approved for Copilot' must have passed a documented review covering schema scoping, descriptions, verified answers and a golden-question test pass. | G22: Approval is the trust signal shown to users; unapproved models display a warning advising users to inspect results and contact the owner. Rubber-stamping approval destroys the signal's value. | I22: (manual) For each approved model, confirm a review record exists with a date, reviewer, and golden-question pass rate. [expected: review record per approved model] | J22: Define the approval checklist from this rule pack and gate the flag behind it. | K22: The approval badge becomes noise and users cannot tell prepared models from unprepared ones. | L22: Copilot in Power BI tutorial: prepare a semantic model for AI; Copilot and Agent admin settings | M22: documented | N22: unknown
A23: WSP-005 | B23: Reports, dashboards and apps cannot be approved - only semantic models | C23: low | D23: limit | E23: copilot-powerbi | F23: Governance documentation must state that there is currently no way to mark a report, dashboard or app as approved for Copilot; only semantic models carry the flag. | G23: Teams design approval workflows around reports and then find the flag does not exist, leaving the process half-implemented. | I23: (manual) Confirm the governance doc reflects the model-only scope of approval. [expected: documented] | J23: Anchor the approval process on semantic models and treat report quality as a separate control. | K23: Approval process design churn. | L23: Prepare your data for AI to improve Copilot results (preview) | M23: documented | N23: unknown
A24: WSP-006 | B24: Semantic model description is populated for discovery | C24: high | D24: metadata | E24: copilot-powerbi | F24: Each in-scope semantic model must have a populated description in model settings that names the subject areas, key entities and the questions it is meant to answer. | G24: Descriptions feed the Search grounding path, which is how standalone Copilot decides which model to use for a question. A blank description makes the model effectively invisible or, worse, picked at random. | I24: (api) Read the model description for every in-scope model; flag empty, default, or single-word values. [expected: non-empty, keyword-rich description] | J24: Write a description covering tables, measures, relationships and intended audience, using distinct keywords rather than generic phrasing. | K24: Standalone Copilot routes questions to the wrong model. | L24: Copilot in Power BI tutorial: prepare a semantic model for AI; Frequently asked questions about preparing data for AI | M24: documented | N24: unknown
A25: WSP-007 | B25: Report descriptions are populated where reports are part of the AI surface | C25: medium | D25: metadata | E25: copilot-powerbi | F25: Reports exposed to Copilot should carry a description in File > Settings that provides natural-language context for data discovery. | G25: Report descriptions contribute to discovery and to the report summary experience. | I25: (manual) Sample in-scope reports and check for a populated description. [expected: non-empty description] | J25: Add a one-to-two sentence description naming the analysis and its dimensions. | K25: Weaker discovery and less useful report summaries. | L25: Copilot in Power BI tutorial: prepare a semantic model for AI | M25: documented | N25: unknown
A26: SCH-001 | B26: An AI data schema is explicitly defined for every in-scope semantic model | C26: blocker | D26: config | E26: copilot-powerbi, fabric-data-agent | F26: Every semantic model exposed to Copilot or bound to a data agent must have an AI data schema defined through Prep data for AI, rather than defaulting to the full model surface. | G26: This is the primary control against the ad-hoc-SQL-server behaviour. The DAX generation tool uses only the AI data schema. If you never define one, the generator reasons over everything you own. | I26: (tmdl) Inspect the model's LSDL / AI data schema definition. Confirm a curated selection exists and is narrower than the full object list. [expected: defined and narrower than full model] | J26: Open Prep data for AI > Simplify the data schema and deselect every field not required by the intended question set. | K26: The generator considers every table, column and measure on every question - maximum latency, maximum token cost, maximum ambiguity. | L26: Copilot in Power BI tutorial: prepare a semantic model for AI; Semantic model best practices for data agent; Prepare your data for AI to improve Copilot results (preview) | M26: documented | N26: unknown
A27: SCH-002 | B27: Model entity count stays within the 1,000-entity indexing ceiling | C27: critical | D27: limit | E27: copilot-powerbi, fabric-data-agent | F27: The combined count of tables and columns in the model should stay at or below 1,000 entities, or the AI data schema must reduce the exposed surface to below that ceiling. | G27: Power BI indexes a maximum of 1,000 model entities (tables and columns combined) for instance-value search. Beyond that, columns go unindexed and value-based filtering silently degrades. | H27: 1000 entities (tables + columns) (hard) | I27: (dax) Count tables plus columns via INFO.TABLES()/INFO.COLUMNS() or a VPAX extract. Compare against 1000. [lte 1000 entities] | J27: Trim the model, or narrow the AI data schema so the AI-visible entity count is well under the ceiling. Aim materially below 1,000, not at it. | K27: Columns are skipped during indexing; Copilot cannot resolve filter values it should be able to find. | L27: Frequently asked questions about preparing data for AI | M27: documented | N27: unknown
A28: SCH-003 | B28: Instance-value indexing stays within the 5 million value ceiling | C28: critical | D28: limit | E28: copilot-powerbi | F28: The total indexed instance values across the model must stay under 5 million, and high-cardinality columns must be excluded from the AI data schema where they are not needed for filtering. | G28: Indexing stops at 5 million instance values. When the next column would push the total over, Power BI skips that column entirely - and it may be a column that matters. A single high-cardinality key can consume the budget and starve every column after it. | H28: 5000000 instance values (hard) | I28: (dax) Estimate distinct-value counts per AI-visible column (APPROXIMATEDISTINCTCOUNT or COLUMNSTATISTICS) and sum. Compare against 5,000,000. [lte 5000000 instance values] | J28: Deselect surrogate keys, GUIDs, free-text notes and transaction identifiers from the AI data schema. Keep the columns users actually name in questions. | K28: Arbitrary columns silently unindexed; value filters fail unpredictably and look like model bugs. | L28: Frequently asked questions about preparing data for AI | M28: documented | N28: unknown
A29: SCH-004 | B29: Filterable text values are under 100 characters | C29: high | D29: limit | E29: copilot-powerbi | F29: Columns intended for value-based filtering by Copilot must contain values shorter than 100 characters. | G29: Text values of 100 characters or more are not indexed. Long descriptive strings will never be matched by a user's natural-language filter no matter how the question is phrased. | H29: 100 characters (hard) | I29: (dax) For each AI-visible text column, compute MAX(LEN(column)). Flag any column used for filtering whose values reach 100 characters. [lt 100 characters] | J29: Split long text into a short filterable code or category column plus a long descriptive column, and expose only the short one to the AI data schema. | K29: Users filter on a value that visibly exists in the report and Copilot insists it cannot find it. | L29: Frequently asked questions about preparing data for AI | M29: documented | N29: unknown
A30: SCH-005 | B30: Copilot Diagnostics shows no AgentSchemaReduced warning | C30: critical | D30: validation | E30: copilot-powerbi | F30: Copilot Diagnostics must not report 'AgentSchemaReduced' for in-scope models under representative questions. | G30: AgentSchemaReduced means the schema was too large for Copilot to render and Copilot automatically cut it down - by its own choice, not yours. Whatever it dropped is invisible to the generator and you did not decide what went. | I30: (manual) Run the golden question set and inspect Copilot Diagnostics warnings for AgentSchemaReduced. [expected: warning absent] | J30: Reduce the AI data schema yourself until the warning clears, so schema reduction is a deliberate curation decision rather than an automatic truncation. | K30: Silent, uncontrolled loss of schema; answers omit data that exists and nobody can explain why. | L30: Frequently asked questions about preparing data for AI | M30: documented | N30: unknown
A31: SCH-006 | B31: Surrogate keys and relationship identifiers are removed from the AI schema | C31: high | D31: modeling | E31: copilot-powerbi, fabric-data-agent | F31: Unique identifier columns used only to define relationships must be deselected from the AI data schema. | G31: Documented explicitly as a field type to deselect. Keys carry no business meaning, add cardinality against the indexing budget, and invite the generator to join or group on them. | I31: (tmdl) List AI-visible columns whose names match key patterns (ID, Key, SK, GUID, Code suffixes) and confirm exclusion unless deliberately kept. [expected: excluded] | J31: Deselect them in Simplify the data schema. Relationships still work; the generator just stops seeing the keys. | K31: Grouping by meaningless identifiers, wasted index budget, and joins the generator invents rather than follows. | L31: Copilot in Power BI tutorial: prepare a semantic model for AI; Best practices for configuring your data agent | M31: documented | N31: unknown
A32: SCH-007 | B32: Sort-order and helper columns are removed from the AI schema | C32: high | D32: modeling | E32: copilot-powerbi | F32: Sort-by columns such as Month (Sort Order) or Day (Sort Order), and other presentation helper columns, must be deselected from the AI data schema. | G32: Called out explicitly as fields to deselect. They duplicate a real attribute in numeric form, so the generator has two plausible columns for one concept and picks wrong roughly half the time. | I32: (tmdl) Identify columns used as Sort By Column targets and confirm they are excluded from the AI schema. [expected: excluded] | J32: Deselect all sort-order columns. Sorting behaviour in visuals is unaffected. | K32: Answers grouped by 1..12 instead of month names; user trust erodes on cosmetic-looking errors. | L32: Copilot in Power BI tutorial: prepare a semantic model for AI | M32: documented | N32: unknown
A33: SCH-008 | B33: Archived, staging and audit tables are excluded | C33: high | D33: modeling | E33: copilot-powerbi, fabric-data-agent | F33: Archived, staging, audit and unrelated tables must be excluded from both the AI data schema and any data agent object selection. | G33: Explicit guidance for data agent configuration: select only the tables, columns, views and functions needed for the intended questions. Staging tables are the classic source of near-duplicate results. | I33: (manual) Review the AI-visible table list against the intended question set; flag any table that no in-scope question needs. [expected: excluded] | J33: Remove them from selection. If they must stay in the model for lineage, hide them and exclude them from the AI schema. | K33: The generator queries a staging copy and returns numbers that do not tie to any published report. | L33: Best practices for configuring your data agent | M33: documented | N33: unknown
A34: SCH-009 | B34: AI data schema is scoped to a declared question set | C34: critical | D34: governance | E34: copilot-powerbi, fabric-data-agent | F34: Each AI data schema must be traceable to a written statement of the question scope the model is meant to serve, and every included object must be justified by at least one question in that scope. | G34: 'Select only relevant objects based on the data agent's question scope to reduce ambiguity and latency.' Without a declared scope, inclusion decisions are arbitrary and the schema only ever grows. | I34: (manual) Confirm a question-scope document exists per model/agent and that schema inclusions map to it. [expected: documented question scope] | J34: Write the scope statement first, derive the schema from it, and reject additions that no scoped question requires. | K34: Schema sprawl returns within two release cycles and undoes every other tuning effort. | L34: Semantic model best practices for data agent; Best practices for configuring your data agent | M34: documented | N34: unknown
A35: SCH-010 | B35: Data agent object selection matches the model's AI data schema | C35: critical | D35: config | E35: fabric-data-agent | F35: For a semantic model bound to a data agent, the tables selected in the data agent must be the same tables defined in the model's Prep for AI AI data schema. | G35: Stated as a direct consistency rule. Divergence means the agent exposes objects the DAX generator was never configured to reason about. | I35: (manual) Diff the agent's selected object list against the model's AI data schema. The sets must match. [expected: identical object sets] | J35: Reconcile the two selections and add a check to the release process so they cannot drift. | K35: Objects visible to the agent but absent from the generation schema produce failed or nonsensical DAX. | L35: Semantic model best practices for data agent | M35: documented | N35: unknown
A36: SCH-011 | B36: Dependent objects of selected measures are included in the schema | C36: critical | D36: config | E36: copilot-powerbi, fabric-data-agent | F36: When a measure is included in the AI data schema, every object it depends on must also be included. | G36: Explicit dependency rule; Semantic Link Labs' get_measure_dependencies is the recommended way to enumerate them. A measure whose dependencies were trimmed away fails at query time. | I36: (api) Run get_measure_dependencies (Semantic Link Labs) across AI-visible measures and confirm every dependency is also AI-visible. [expected: all dependencies present] | J36: Add the missing dependencies, or drop the measure from the schema if its dependencies must stay hidden. | K36: Generated DAX references objects the generator believes exist and the query errors. | L36: Semantic model best practices for data agent | M36: documented | N36: unknown
A37: SCH-012 | B37: Hidden fields are not silently relied upon | C37: critical | D37: config | E37: copilot-powerbi, fabric-data-agent | F37: Any field that Copilot must be able to use has to be visible; hidden measures and columns are excluded from grounding and must not appear in verified answers. | G37: Hidden fields are excluded from grounding data, and verified answers referencing hidden columns simply do not work. Teams routinely hide a column for report tidiness and then wonder why Copilot cannot answer about it. | I37: (dax) List objects referenced by verified answers and by the question scope, and confirm none are hidden. [expected: no hidden objects in AI scope] | J37: Unhide the fields Copilot needs, or rewrite the verified answer against visible equivalents. | K37: Verified answers fail silently and Copilot claims data it can see in reports does not exist. | L37: Use Copilot with semantic models in Power BI; Semantic model best practices for data agent | M37: documented | N37: unknown
A38: SCH-013 | B38: Private tables are understood to be entirely invisible to Copilot | C38: high | D38: config | E38: copilot-powerbi | F38: Tables marked private must be documented as fully excluded from all Copilot grounding, and no AI capability may depend on them. | G38: Copilot ignores private tables entirely across both the data-question and DAX query view paths. This is a useful deliberate exclusion mechanism, but a trap when unintentional. | I38: (tmdl) List tables marked private and confirm no in-scope question depends on them. [expected: documented and no dependency] | J38: Use the private flag deliberately to fence off sensitive or technical tables; unmark any table Copilot legitimately needs. | K38: Unexplainable gaps in Copilot's knowledge of the model. | L38: Use Copilot with semantic models in Power BI | M38: documented | N38: unknown
A39: SCH-014 | B39: Duplicate field names across tables are eliminated or disambiguated | C39: high | D39: modeling | E39: copilot-powerbi, fabric-data-agent | F39: The AI-visible schema must not contain identically named fields in multiple tables unless each carries a description that distinguishes it. | G39: Called out directly: 'Name' in a Customer table versus a Store table forces the generator to guess. Ambiguity at schema level cannot be recovered by a better prompt. | I39: (dax) Group AI-visible column and measure names; flag any name appearing in more than one table. [equals 0] | J39: Rename to Customer Name / Store Name, or add distinguishing descriptions to each. | K39: Roughly random field selection on any question naming the ambiguous term. | L39: Copilot in Power BI tutorial: prepare a semantic model for AI; Semantic model best practices for data agent | M39: documented | N39: unknown
A40: SCH-015 | B40: Instance-value reindexing cadence is understood and accounted for | C40: medium | D40: performance | E40: copilot-powerbi | F40: The team must document the reindexing behaviour that applies to each model type and set user expectations accordingly. | G40: Import models reindex on manual or scheduled refresh, but only when Copilot or Q&A has been used in the last 14 days. DirectQuery and Direct Lake reindex when the index is older than 24 hours under the same 14-day activity condition, with COLUMNSTATISTICS cached for 7 days. A model nobody has asked a question of for two weeks stops being reindexed. | H40: activityWindowDays=14; directQueryReindexHours=24; columnStatisticsCacheDays=7; firstIndexMinutes=15 mixed (hard) | I40: (manual) Confirm the operations runbook records the reindexing rules per model type and the 14-day activity dependency. [expected: documented] | J40: Document it, and for low-traffic but important models schedule a periodic synthetic question to keep the model within the activity window. | K40: Stale instance values produce filter misses that look like data errors. | L40: Frequently asked questions about preparing data for AI | M40: documented | N40: unknown
A41: SCH-016 | B41: DirectQuery indexing constraints are accepted or mitigated | C41: medium | D41: limit | E41: copilot-powerbi | F41: For DirectQuery models, confirm the source supports APPROXIMATEDISTINCTCOUNT and accept that indexing occurs at most once per 24 hours unless the model is republished. | G41: Only columns from sources supporting APPROXIMATEDISTINCTCOUNT are indexed at all. A failed underlying refresh leaves a stale index until the next successful one. | I41: (manual) For each DirectQuery model, record source support for APPROXIMATEDISTINCTCOUNT and the observed index age. [expected: documented] | J41: Where the source does not support it, consider Import or Direct Lake for the AI-facing model. | K41: Value filtering effectively unavailable on DirectQuery models against unsupported sources. | L41: Frequently asked questions about preparing data for AI | M41: documented | N41: unknown
A42: SCH-017 | B42: Prep for AI changes are given time to propagate before re-testing | C42: low | D42: operations | E42: copilot-powerbi | F42: Test cycles must allow up to 24 hours for Prep for AI changes to affect Copilot results, typically within an hour, with the longer tail on models that have many attached reports. | G42: Re-testing five minutes after a change and concluding the change did nothing leads to thrashing the configuration. | H42: 24 hours (soft) | I42: (manual) Confirm the test procedure documents the propagation window. [expected: documented] | J42: Build the wait into the evaluation cadence; batch configuration changes rather than tuning one setting at a time. | K42: Configuration churn and false conclusions about which settings help. | L42: Prepare your data for AI to improve Copilot results (preview) | M42: documented | N42: unknown
A43: SCH-018 | B43: Prep for AI edits deployed via Git or pipelines are followed by a refresh | C43: high | D43: operations | E43: copilot-powerbi | F43: After deploying LSDL or Prep for AI changes through Git integration or deployment pipelines, the model must be refreshed in the Power BI service to sync the changes. | G43: Explicit requirement. Import models must be refreshed; DirectQuery and Direct Lake models must be refreshed but only once a day. Skipping this leaves production running the previous AI configuration while source control says otherwise. | I43: (manual) Confirm the deployment pipeline includes a post-deployment refresh step for AI-configured models. [expected: refresh step present] | J43: Add the refresh to the release pipeline and verify the AI configuration post-deployment rather than assuming it landed. | K43: Deployed AI configuration silently inactive in production. | L43: Prepare your data for AI to improve Copilot results (preview) | M43: documented | N43: unknown
A44: SCH-019 | B44: Connection type is supported for Desktop-based Prep for AI authoring | C44: medium | D44: limit | E44: copilot-powerbi | F44: Where Prep for AI is authored in Power BI Desktop, the model must use Import, DirectQuery or local Composite mode. | G44: Power BI Desktop supports only those connection types for Prep data for AI. All model types can use the features in the Power BI service, so the constraint is on where you author, not where you consume. | I44: (manual) Record the connection type of each model and where its AI configuration is authored. | J44: Author Prep for AI in the service for model types Desktop does not support. | K44: Prep for AI unavailable in Desktop and the team assumes the feature is broken. | L44: Prepare your data for AI to improve Copilot results (preview) | M44: documented | N44: unknown
A45: SCH-020 | B45: Data agent stays within the five data source limit and uses the minimum needed | C45: critical | D45: limit | E45: fabric-data-agent | F45: A data agent must be bound to no more than five data sources, and to the fewest sources that its question scope actually requires. | G45: Five sources is a hard cap in any combination across Lakehouses, Warehouses, semantic models, KQL databases, mirrored databases, ontologies and Microsoft Graph. Every additional source widens the routing decision the agent has to make on every question. | H45: 5 data sources per agent (hard) | I45: (api) Count bound data sources per agent and compare against the intended question scope. [lte 5 data sources] | J45: Split broad agents into several narrowly scoped agents rather than binding more sources to one. | K45: At the cap, source routing errors dominate; beyond it, configuration is rejected. | L45: Fabric data agent creation | M45: documented | N45: unknown
